{"version":2,"width":100,"height":26,"timestamp":1690532359,"env":{"SHELL":"","TERM":"xterm"}}
[ 0.00000, "o", "" ]
[ 0.13502, "o", "\u001b[19491001\u001b[1;35m> \u001b[20210325\u001b[0m\u001b[K\u001b[?2004h" ]
[ 0.41620, "o", "#\b# U" ]
[ 0.46758, "o", "s" ]
[ 0.51931, "o", "e" ]
[ 0.57080, "o", " " ]
[ 0.62301, "o", "t" ]
[ 0.67491, "o", "h" ]
[ 0.72626, "o", "e" ]
[ 0.77812, "o", " " ]
[ 0.82964, "o", "`" ]
[ 0.88201, "o", "x" ]
[ 0.93339, "o", " " ]
[ 0.98536, "o", "g" ]
[ 1.03768, "o", "l" ]
[ 1.09024, "o", "o" ]
[ 1.14238, "o", "w" ]
[ 1.19400, "o", "`" ]
[ 1.24595, "o", " " ]
[ 1.29755, "o", "c" ]
[ 1.34993, "o", "o" ]
[ 1.40171, "o", "m" ]
[ 1.45355, "o", "m" ]
[ 1.50556, "o", "a" ]
[ 1.55721, "o", "n" ]
[ 1.60894, "o", "d" ]
[ 1.66052, "o", " " ]
[ 1.71200, "o", "f" ]
[ 1.76356, "o", "o" ]
[ 1.81559, "o", "r" ]
[ 1.86738, "o", "m" ]
[ 1.91886, "o", "a" ]
[ 1.97051, "o", "t" ]
[ 2.02193, "o", " " ]
[ 2.07383, "o", "t" ]
[ 2.12520, "o", "o" ]
[ 2.17779, "o", " " ]
[ 2.23000, "o", "q" ]
[ 2.28232, "o", "u" ]
[ 2.33423, "o", "i" ]
[ 2.38584, "o", "c" ]
[ 2.43770, "o", "k" ]
[ 2.48923, "o", "l" ]
[ 2.54178, "o", "y" ]
[ 2.59344, "o", " " ]
[ 2.64564, "o", "u" ]
[ 2.69729, "o", "s" ]
[ 2.74936, "o", "e" ]
[ 2.80123, "o", " " ]
[ 2.85279, "o", "t" ]
[ 2.90447, "o", "h" ]
[ 2.95587, "o", "e" ]
[ 3.00778, "o", " " ]
[ 3.05926, "o", "`" ]
[ 3.11120, "o", "g" ]
[ 3.16314, "o", "l" ]
[ 3.21492, "o", "o" ]
[ 3.26683, "o", "w" ]
[ 3.31828, "o", "`" ]
[ 3.37007, "o", " " ]
[ 3.42153, "o", "c" ]
[ 3.47359, "o", "o" ]
[ 3.52506, "o", "m" ]
[ 3.57706, "o", "m" ]
[ 3.62909, "o", "a" ]
[ 3.68051, "o", "n" ]
[ 3.73271, "o", "d" ]
[ 3.78422, "o", "\u001b[?2004l\r\r\n" ]
[ 3.78441, "o", "\u001b[1m\u001b[7m#\u001b[27m\u001b[1m\u001b[0m                                                                                                   \r \r\r\u001b[0m\u001b[27m\u001b[24m\u001b[J\r\n\u001b[19491001\u001b[1;35m> \u001b[20210325\u001b[0m\u001b[K\u001b[?2004h" ]
[ 5.28813, "o", "x" ]
[ 5.33996, "o", "\bx " ]
[ 5.39170, "o", "g" ]
[ 5.44309, "o", "l" ]
[ 5.49496, "o", "o" ]
[ 5.54646, "o", "w" ]
[ 5.59886, "o", " " ]
[ 5.65049, "o", "-" ]
[ 5.70226, "o", "-" ]
[ 5.75423, "o", "v" ]
[ 5.80601, "o", "e" ]
[ 5.85779, "o", "r" ]
[ 5.90915, "o", "s" ]
[ 5.96102, "o", "i" ]
[ 6.01246, "o", "o" ]
[ 6.06514, "o", "n" ]
[ 6.31926, "o", "\u001b[?2004l\r\r\n" ]
[ 6.46900, "o", "glow version 1.5.1 (ad21129)\r\n" ]
[ 6.46981, "o", "\u001b[1m\u001b[7m#\u001b[27m\u001b[1m\u001b[0m                                                                                                   \r \r\r\u001b[0m\u001b[27m\u001b[24m\u001b[J\r\n\u001b[19491001\u001b[1;35m> \u001b[20210325\u001b[0m\u001b[K\u001b[?2004h" ]
[ 7.32106, "o", "#" ]
[ 7.32121, "o", "\b# U" ]
[ 7.37368, "o", "s" ]
[ 7.42527, "o", "i" ]
[ 7.47745, "o", "n" ]
[ 7.52944, "o", "g" ]
[ 7.58145, "o", " " ]
[ 7.63301, "o", "`" ]
[ 7.68493, "o", "x" ]
[ 7.73654, "o", " " ]
[ 7.78799, "o", "e" ]
[ 7.84018, "o", "n" ]
[ 7.89191, "o", "v" ]
[ 7.94403, "o", " " ]
[ 7.99567, "o", "u" ]
[ 8.04764, "o", "s" ]
[ 8.09950, "o", "e" ]
[ 8.15104, "o", "`" ]
[ 8.20353, "o", " " ]
[ 8.25505, "o", "c" ]
[ 8.30687, "o", "a" ]
[ 8.35881, "o", "n" ]
[ 8.41031, "o", " " ]
[ 8.46206, "o", "a" ]
[ 8.51360, "o", "u" ]
[ 8.56516, "o", "t" ]
[ 8.61664, "o", "o" ]
[ 8.66828, "o", "m" ]
[ 8.71997, "o", "a" ]
[ 8.77167, "o", "t" ]
[ 8.82328, "o", "i" ]
[ 8.87472, "o", "c" ]
[ 8.92657, "o", "a" ]
[ 8.97796, "o", "l" ]
[ 9.02985, "o", "l" ]
[ 9.08138, "o", "y" ]
[ 9.13314, "o", " " ]
[ 9.18530, "o", "i" ]
[ 9.23674, "o", "n" ]
[ 9.28833, "o", "s" ]
[ 9.33984, "o", "t" ]
[ 9.39148, "o", "a" ]
[ 9.44291, "o", "l" ]
[ 9.49454, "o", "l" ]
[ 9.54738, "o", " " ]
[ 9.59973, "o", "a" ]
[ 9.65166, "o", "n" ]
[ 9.70313, "o", "d" ]
[ 9.75465, "o", " " ]
[ 9.80623, "o", "c" ]
[ 9.85844, "o", "o" ]
[ 9.90985, "o", "n" ]
[ 9.96198, "o", "f" ]
[ 10.01374, "o", "i" ]
[ 10.06516, "o", "g" ]
[ 10.11741, "o", "u" ]
[ 10.16901, "o", "r" ]
[ 10.22093, "o", "e" ]
[ 10.27253, "o", " " ]
[ 10.32483, "o", "c" ]
[ 10.37653, "o", "o" ]
[ 10.42829, "o", "r" ]
[ 10.47998, "o", "r" ]
[ 10.53186, "o", "e" ]
[ 10.58333, "o", "s" ]
[ 10.63501, "o", "p" ]
[ 10.68653, "o", "o" ]
[ 10.73819, "o", "n" ]
[ 10.79001, "o", "d" ]
[ 10.84194, "o", "i" ]
[ 10.89363, "o", "n" ]
[ 10.94556, "o", "g" ]
[ 10.99693, "o", " " ]
[ 11.04879, "o", "g" ]
[ 11.10021, "o", "l" ]
[ 11.15289, "o", "o" ]
[ 11.20436, "o", "b" ]
[ 11.25618, "o", "a" ]
[ 11.30835, "o", "l" ]
[ 11.36007, "o", " " ]
[ 11.41163, "o", "e" ]
[ 11.46351, "o", "n" ]
[ 11.51550, "o", "v" ]
[ 11.56694, "o", "i" ]
[ 11.61921, "o", "r" ]
[ 11.67091, "o", "o" ]
[ 11.72292, "o", "n" ]
[ 11.77437, "o", "m" ]
[ 11.82591, "o", "e" ]
[ 11.87752, "o", "n" ]
[ 11.92923, "o", "t" ]
[ 11.98160, "o", " " ]
[ 12.03340, "o", "v" ]
[ 12.08531, "o", "a" ]
[ 12.13695, "o", "r" ]
[ 12.18860, "o", "i" ]
[ 12.24060, "o", "a \r\u001b[K" ]
[ 12.29240, "o", "b" ]
[ 12.34412, "o", "\rbl" ]
[ 12.39575, "o", "e" ]
[ 12.44771, "o", "s" ]
[ 12.49931, "o", "\u001b[?2004l\r\r\n" ]
[ 12.49951, "o", "\u001b[1m\u001b[7m#\u001b[27m\u001b[1m\u001b[0m                                                                                                   \r \r\r\u001b[0m\u001b[27m\u001b[24m\u001b[J\r\n\u001b[19491001\u001b[1;35m> \u001b[20210325\u001b[0m\u001b[K\u001b[?2004h" ]
[ 14.00297, "o", "x" ]
[ 14.05452, "o", "\bx " ]
[ 14.10656, "o", "e" ]
[ 14.15802, "o", "n" ]
[ 14.20962, "o", "v" ]
[ 14.26226, "o", " " ]
[ 14.31391, "o", "u" ]
[ 14.36589, "o", "s" ]
[ 14.41716, "o", "e" ]
[ 14.46885, "o", " " ]
[ 14.52031, "o", "g" ]
[ 14.57229, "o", "l" ]
[ 14.62396, "o", "o" ]
[ 14.67537, "o", "w" ]
[ 14.92902, "o", "\u001b[?2004l\r\r\n" ]
[ 15.05795, "o", "- \u001b[32mI\u001b[0m\u001b[32m|pkg: \u001b[0mSuccessfully set link from path \u001b[0m\r\n" ]
[ 15.07990, "o", "- \u001b[32mI\u001b[0m\u001b[32m|env: \u001b[0mSuccessfully set glow=v0.0.1 in the current environment.\u001b[0m\r\n" ]
[ 15.13760, "o", "- \u001b[32mI\u001b[0m\u001b[32m|env: \u001b[0mConfig file updated to /root/.x-cmd.root/local/data/env/version\u001b[0m\r\n" ]
[ 15.13776, "o", "\u001b[1m\u001b[7m#\u001b[27m\u001b[1m\u001b[0m                                                                                                   \r \r\r\u001b[0m\u001b[27m\u001b[24m\u001b[J\r\n\u001b[19491001\u001b[1;35m> \u001b[20210325\u001b[0m\u001b[K" ]
[ 15.13789, "o", "\u001b[?2004h" ]
[ 15.93084, "o", "#\b# U" ]
[ 15.98310, "o", "s" ]
[ 16.03518, "o", "i" ]
[ 16.08664, "o", "n" ]
[ 16.13870, "o", "g" ]
[ 16.19049, "o", " " ]
[ 16.24274, "o", "G" ]
[ 16.29450, "o", "l" ]
[ 16.34628, "o", "o" ]
[ 16.39818, "o", "w" ]
[ 16.44988, "o", "'" ]
[ 16.50188, "o", "s" ]
[ 16.55339, "o", " " ]
[ 16.60524, "o", "U" ]
[ 16.65712, "o", "I" ]
[ 16.70891, "o", " " ]
[ 16.76043, "o", "i" ]
[ 16.81231, "o", "n" ]
[ 16.86387, "o", "t" ]
[ 16.91559, "o", "e" ]
[ 16.96758, "o", "r" ]
[ 17.01925, "o", "f" ]
[ 17.07110, "o", "a" ]
[ 17.12266, "o", "c" ]
[ 17.17468, "o", "e" ]
[ 17.22628, "o", "\u001b[?2004l\r\r\n\u001b[1m\u001b[7m#\u001b[27m\u001b[1m\u001b[0m                                                                                                   \r \r\r\u001b[0m\u001b[27m\u001b[24m\u001b[J\r\n\u001b[19491001\u001b[1;35m> \u001b[20210325\u001b[0m\u001b[K\u001b[?2004h" ]
[ 18.72977, "o", "g" ]
[ 18.78174, "o", "\bgl" ]
[ 18.83402, "o", "o" ]
[ 18.88557, "o", "w" ]
[ 19.43963, "o", "\u001b[?2004l\r\r\n" ]
[ 19.46289, "o", "\u001b]11;?\u001b\\\u001b[6n" ]
[ 19.46444, "o", "\u001b]11;?\u001b\\\u001b[6n" ]
[ 19.46565, "o", "\u001b]10;?\u001b\\\u001b[6n" ]
[ 19.46694, "o", "\u001b]11;?\u001b\\\u001b[6n" ]
[ 19.46823, "o", "\u001b[?25l\u001b[?1049h\u001b[2J\u001b[1;1H\u001b[1;1H\u001b[?25l" ]
[ 19.48526, "o", "\r\r\n / \u001b[1;;m Glow \u001b[0m\r\r\n \r\r\n   1 local │ 0 stashed │ 0 news\r\r\n \r\r\n │ README.md\r\r\n │ just now\r\r\n \r\r\n \r\r\n \r\r\n \r\r\n \r\r\n \r\r\n \r\r\n \r\r\n \r\r\n \r\r\n \r\r\n \r\r\n \r\r\n \r\r\n \r\r\n   \r\r\n \r\r\n   tab section • / find • e edit • q quit • ? more\r\r\n\u001b[26;0H" ]
[ 19.58611, "o", "\u001b[1A\u001b[1A\u001b[1A\u001b[1A\u001b[1A\u001b[1A\u001b[1A\u001b[1A\u001b[1A\u001b[1A\u001b[1A\u001b[1A\u001b[1A\u001b[1A\u001b[1A\u001b[1A\u001b[1A\u001b[1A\u001b[1A\u001b[1A\u001b[1A\u001b[1A\u001b[1A\u001b[1A\u001b[2K\u001b[1A\u001b[100D\u001b[2K\r\r\n - \u001b[1;;m Glow \u001b[0m\r\r\n\u001b[1B\u001b[1B\u001b[1B\u001b[1B\u001b[1B\u001b[1B\u001b[1B\u001b[1B\u001b[1B\u001b[1B\u001b[1B\u001b[1B\u001b[1B\u001b[1B\u001b[1B\u001b[1B\u001b[1B\u001b[1B\u001b[1B\u001b[1B\u001b[1B\u001b[1B\u001b[1B\u001b[26;0H" ]
[ 19.68572, "o", "\u001b[1A\u001b[1A\u001b[1A\u001b[1A\u001b[1A\u001b[1A\u001b[1A\u001b[1A\u001b[1A\u001b[1A\u001b[1A\u001b[1A\u001b[1A\u001b[1A\u001b[1A\u001b[1A\u001b[1A\u001b[1A\u001b[1A\u001b[1A\u001b[1A\u001b[1A\u001b[1A\u001b[1A\u001b[2K\u001b[1A\u001b[100D\u001b[2K\r\r\n \\ \u001b[1;;m Glow \u001b[0m\r\r\n\u001b[1B\u001b[1B\u001b[1B\u001b[1B\u001b[1B\u001b[1B\u001b[1B\u001b[1B\u001b[1B\u001b[1B\u001b[1B\u001b[1B\u001b[1B\u001b[1B\u001b[1B\u001b[1B\u001b[1B\u001b[1B\u001b[1B\u001b[1B\u001b[1B\u001b[1B\u001b[1B\u001b[26;0H" ]
[ 19.78528, "o", "\u001b[1A\u001b[1A\u001b[1A\u001b[1A\u001b[1A\u001b[1A\u001b[1A\u001b[1A\u001b[1A\u001b[1A\u001b[1A\u001b[1A\u001b[1A\u001b[1A\u001b[1A\u001b[1A\u001b[1A\u001b[1A\u001b[1A\u001b[1A\u001b[1A\u001b[1A\u001b[1A\u001b[1A\u001b[2K\u001b[1A\u001b[100D\u001b[2K\r\r\n | \u001b[1;;m Glow \u001b[0m\r\r\n\u001b[1B\u001b[1B\u001b[1B\u001b[1B\u001b[1B\u001b[1B\u001b[1B\u001b[1B\u001b[1B\u001b[1B\u001b[1B\u001b[1B\u001b[1B\u001b[1B\u001b[1B\u001b[1B\u001b[1B\u001b[1B\u001b[1B\u001b[1B\u001b[1B\u001b[1B\u001b[1B\u001b[26;0H" ]
[ 19.88528, "o", "\u001b[1A\u001b[1A\u001b[1A\u001b[1A\u001b[1A\u001b[1A\u001b[1A\u001b[1A\u001b[1A\u001b[1A\u001b[1A\u001b[1A\u001b[1A\u001b[1A\u001b[1A\u001b[1A\u001b[1A\u001b[1A\u001b[1A\u001b[1A\u001b[1A\u001b[1A\u001b[1A\u001b[1A\u001b[2K\u001b[1A\u001b[100D\u001b[2K\r\r\n / \u001b[1;;m Glow \u001b[0m\r\r\n\u001b[1B\u001b[1B\u001b[1B\u001b[1B\u001b[1B\u001b[1B\u001b[1B\u001b[1B\u001b[1B\u001b[1B\u001b[1B\u001b[1B\u001b[1B\u001b[1B\u001b[1B\u001b[1B\u001b[1B\u001b[1B\u001b[1B\u001b[1B\u001b[1B\u001b[1B\u001b[1B\u001b[26;0H" ]
[ 19.98572, "o", "\u001b[1A\u001b[1A\u001b[1A\u001b[1A\u001b[1A\u001b[1A\u001b[1A\u001b[1A\u001b[1A\u001b[1A\u001b[1A\u001b[1A\u001b[1A\u001b[1A\u001b[1A\u001b[1A\u001b[1A\u001b[1A\u001b[1A\u001b[1A\u001b[1A\u001b[1A\u001b[1A\u001b[1A\u001b[2K\u001b[1A\u001b[100D\u001b[2K\r\r\n - \u001b[1;;m Glow \u001b[0m\r\r\n\u001b[1B\u001b[1B\u001b[1B\u001b[1B\u001b[1B\u001b[1B\u001b[1B\u001b[1B\u001b[1B\u001b[1B\u001b[1B\u001b[1B\u001b[1B\u001b[1B\u001b[1B\u001b[1B\u001b[1B\u001b[1B\u001b[1B\u001b[1B\u001b[1B\u001b[1B\u001b[1B\u001b[26;0H" ]
[ 20.08561, "o", "\u001b[1A\u001b[1A\u001b[1A\u001b[1A\u001b[1A\u001b[1A\u001b[1A\u001b[1A\u001b[1A\u001b[1A\u001b[1A\u001b[1A\u001b[1A\u001b[1A\u001b[1A\u001b[1A\u001b[1A\u001b[1A\u001b[1A\u001b[1A\u001b[1A\u001b[1A\u001b[1A\u001b[1A\u001b[2K\u001b[1A\u001b[100D\u001b[2K\r\r\n \\ \u001b[1;;m Glow \u001b[0m\r\r\n\u001b[1B\u001b[1B\u001b[1B\u001b[1B\u001b[1B\u001b[1B\u001b[1B\u001b[1B\u001b[1B\u001b[1B\u001b[1B\u001b[1B\u001b[1B\u001b[1B\u001b[1B\u001b[1B\u001b[1B\u001b[1B\u001b[1B\u001b[1B\u001b[1B\u001b[1B\u001b[1B\u001b[26;0H" ]
[ 20.18518, "o", "\u001b[1A\u001b[1A\u001b[1A\u001b[1A\u001b[1A\u001b[1A\u001b[1A\u001b[1A\u001b[1A\u001b[1A\u001b[1A\u001b[1A\u001b[1A\u001b[1A\u001b[1A\u001b[1A\u001b[1A\u001b[1A\u001b[1A\u001b[1A\u001b[1A\u001b[1A\u001b[1A\u001b[1A\u001b[2K\u001b[1A\u001b[100D\u001b[2K\r\r\n | \u001b[1;;m Glow \u001b[0m\r\r\n\u001b[1B\u001b[1B\u001b[1B\u001b[1B\u001b[1B\u001b[1B\u001b[1B\u001b[1B\u001b[1B\u001b[1B\u001b[1B\u001b[1B\u001b[1B\u001b[1B\u001b[1B\u001b[1B\u001b[1B\u001b[1B\u001b[1B\u001b[1B\u001b[1B\u001b[1B\u001b[1B\u001b[26;0H" ]
[ 20.28608, "o", "\u001b[1A\u001b[1A\u001b[1A\u001b[1A\u001b[1A\u001b[1A\u001b[1A\u001b[1A\u001b[1A\u001b[1A\u001b[1A\u001b[1A\u001b[1A\u001b[1A\u001b[1A\u001b[1A\u001b[1A\u001b[1A\u001b[1A\u001b[1A\u001b[1A\u001b[1A\u001b[1A\u001b[1A\u001b[2K\u001b[1A\u001b[100D\u001b[2K\r\r\n / \u001b[1;;m Glow \u001b[0m\r\r\n\u001b[1B\u001b[1B\u001b[1B\u001b[1B\u001b[1B\u001b[1B\u001b[1B\u001b[1B\u001b[1B\u001b[1B\u001b[1B\u001b[1B\u001b[1B\u001b[1B\u001b[1B\u001b[1B\u001b[1B\u001b[1B\u001b[1B\u001b[1B\u001b[1B\u001b[1B\u001b[1B\u001b[26;0H" ]
[ 20.38605, "o", "\u001b[1A\u001b[1A\u001b[1A\u001b[1A\u001b[1A\u001b[1A\u001b[1A\u001b[1A\u001b[1A\u001b[1A\u001b[1A\u001b[1A\u001b[1A\u001b[1A\u001b[1A\u001b[1A\u001b[1A\u001b[1A\u001b[1A\u001b[1A\u001b[1A\u001b[1A\u001b[1A\u001b[1A\u001b[2K\u001b[1A\u001b[100D\u001b[2K\r\r\n - \u001b[1;;m Glow \u001b[0m\r\r\n\u001b[1B\u001b[1B\u001b[1B\u001b[1B\u001b[1B\u001b[1B\u001b[1B\u001b[1B\u001b[1B\u001b[1B\u001b[1B\u001b[1B\u001b[1B\u001b[1B\u001b[1B\u001b[1B\u001b[1B\u001b[1B\u001b[1B\u001b[1B\u001b[1B\u001b[1B\u001b[1B\u001b[26;0H" ]
[ 20.48564, "o", "\u001b[1A\u001b[1A\u001b[1A\u001b[1A\u001b[1A\u001b[1A\u001b[1A\u001b[1A\u001b[1A\u001b[1A\u001b[1A\u001b[1A\u001b[1A\u001b[1A\u001b[1A\u001b[1A\u001b[1A\u001b[1A\u001b[1A\u001b[1A\u001b[1A\u001b[1A\u001b[1A\u001b[1A\u001b[2K\u001b[1A\u001b[100D\u001b[2K\r\r\n \\ \u001b[1;;m Glow \u001b[0m\r\r\n\u001b[1B\u001b[1B\u001b[1B\u001b[1B\u001b[1B\u001b[1B\u001b[1B\u001b[1B\u001b[1B\u001b[1B\u001b[1B\u001b[1B\u001b[1B\u001b[1B\u001b[1B\u001b[1B\u001b[1B\u001b[1B\u001b[1B\u001b[1B\u001b[1B\u001b[1B\u001b[1B\u001b[26;0H" ]
[ 20.58533, "o", "\u001b[1A\u001b[1A\u001b[1A\u001b[1A\u001b[1A\u001b[1A\u001b[1A\u001b[1A\u001b[1A\u001b[1A\u001b[1A\u001b[1A\u001b[1A\u001b[1A\u001b[1A\u001b[1A\u001b[1A\u001b[1A\u001b[1A\u001b[1A\u001b[1A\u001b[1A\u001b[1A\u001b[1A\u001b[2K\u001b[1A\u001b[100D\u001b[2K\r\r\n | \u001b[1;;m Glow \u001b[0m\r\r\n\u001b[1B\u001b[1B\u001b[1B\u001b[1B\u001b[1B\u001b[1B\u001b[1B\u001b[1B\u001b[1B\u001b[1B\u001b[1B\u001b[1B\u001b[1B\u001b[1B\u001b[1B\u001b[1B\u001b[1B\u001b[1B\u001b[1B\u001b[1B\u001b[1B\u001b[1B\u001b[1B\u001b[26;0H" ]
[ 20.68605, "o", "\u001b[1A\u001b[1A\u001b[1A\u001b[1A\u001b[1A\u001b[1A\u001b[1A\u001b[1A\u001b[1A\u001b[1A\u001b[1A\u001b[1A\u001b[1A\u001b[1A\u001b[1A\u001b[1A\u001b[1A\u001b[1A\u001b[1A\u001b[1A\u001b[1A\u001b[1A\u001b[1A\u001b[1A\u001b[2K\u001b[1A\u001b[100D\u001b[2K\r\r\n / \u001b[1;;m Glow \u001b[0m\r\r\n\u001b[1B\u001b[1B\u001b[1B\u001b[1B\u001b[1B\u001b[1B\u001b[1B\u001b[1B\u001b[1B\u001b[1B\u001b[1B\u001b[1B\u001b[1B\u001b[1B\u001b[1B\u001b[1B\u001b[1B\u001b[1B\u001b[1B\u001b[1B\u001b[1B\u001b[1B\u001b[1B\u001b[26;0H" ]
[ 20.78572, "o", "\u001b[1A\u001b[1A\u001b[1A\u001b[1A\u001b[1A\u001b[1A\u001b[1A\u001b[1A\u001b[1A\u001b[1A\u001b[1A\u001b[1A\u001b[1A\u001b[1A\u001b[1A\u001b[1A\u001b[1A\u001b[1A\u001b[1A\u001b[1A\u001b[1A\u001b[1A\u001b[1A\u001b[1A\u001b[2K\u001b[1A\u001b[100D\u001b[2K\r\r\n - \u001b[1;;m Glow \u001b[0m\r\r\n\u001b[1B\u001b[1B\u001b[1B\u001b[1B\u001b[1B\u001b[1B\u001b[1B\u001b[1B\u001b[1B\u001b[1B\u001b[1B\u001b[1B\u001b[1B\u001b[1B\u001b[1B\u001b[1B\u001b[1B\u001b[1B\u001b[1B\u001b[1B\u001b[1B\u001b[1B\u001b[1B\u001b[26;0H" ]
[ 20.88561, "o", "\u001b[1A\u001b[1A\u001b[1A\u001b[1A\u001b[1A\u001b[1A\u001b[1A\u001b[1A\u001b[1A\u001b[1A\u001b[1A\u001b[1A\u001b[1A\u001b[1A\u001b[1A\u001b[1A\u001b[1A\u001b[1A\u001b[1A\u001b[1A\u001b[1A\u001b[1A\u001b[1A\u001b[1A\u001b[2K\u001b[1A\u001b[100D\u001b[2K\r\r\n \\ \u001b[1;;m Glow \u001b[0m\r\r\n\u001b[1B\u001b[1B\u001b[1B\u001b[1B\u001b[1B\u001b[1B\u001b[1B\u001b[1B\u001b[1B\u001b[1B\u001b[1B\u001b[1B\u001b[1B\u001b[1B\u001b[1B\u001b[1B\u001b[1B\u001b[1B\u001b[1B\u001b[1B\u001b[1B\u001b[1B\u001b[1B\u001b[26;0H" ]
[ 20.98516, "o", "\u001b[1A\u001b[1A\u001b[1A\u001b[1A\u001b[1A\u001b[1A\u001b[1A\u001b[1A\u001b[1A\u001b[1A\u001b[1A\u001b[1A\u001b[1A\u001b[1A\u001b[1A\u001b[1A\u001b[1A\u001b[1A\u001b[1A\u001b[1A\u001b[1A\u001b[1A\u001b[1A\u001b[1A\u001b[2K\u001b[1A\u001b[100D\u001b[2K\r\r\n | \u001b[1;;m Glow \u001b[0m\r\r\n\u001b[1B\u001b[1B\u001b[1B\u001b[1B\u001b[1B\u001b[1B\u001b[1B\u001b[1B\u001b[1B\u001b[1B\u001b[1B\u001b[1B\u001b[1B\u001b[1B\u001b[1B\u001b[1B\u001b[1B\u001b[1B\u001b[1B\u001b[1B\u001b[1B\u001b[1B\u001b[1B\u001b[26;0H" ]
[ 21.08578, "o", "\u001b[1A\u001b[1A\u001b[1A\u001b[1A\u001b[1A\u001b[1A\u001b[1A\u001b[1A\u001b[1A\u001b[1A\u001b[1A\u001b[1A\u001b[1A\u001b[1A\u001b[1A\u001b[1A\u001b[1A\u001b[1A\u001b[1A\u001b[1A\u001b[1A\u001b[1A\u001b[1A\u001b[1A\u001b[2K\u001b[1A\u001b[100D\u001b[2K\r\r\n / \u001b[1;;m Glow \u001b[0m\r\r\n\u001b[1B\u001b[1B\u001b[1B\u001b[1B\u001b[1B\u001b[1B\u001b[1B\u001b[1B\u001b[1B\u001b[1B\u001b[1B\u001b[1B\u001b[1B\u001b[1B\u001b[1B\u001b[1B\u001b[1B\u001b[1B\u001b[1B\u001b[1B\u001b[1B\u001b[1B\u001b[1B\u001b[26;0H" ]
[ 21.18528, "o", "\u001b[1A\u001b[1A\u001b[1A\u001b[1A\u001b[1A\u001b[1A\u001b[1A\u001b[1A\u001b[1A\u001b[1A\u001b[1A\u001b[1A\u001b[1A\u001b[1A\u001b[1A\u001b[1A\u001b[1A\u001b[1A\u001b[1A\u001b[1A\u001b[1A\u001b[1A\u001b[1A\u001b[1A\u001b[2K\u001b[1A\u001b[100D\u001b[2K\r\r\n - \u001b[1;;m Glow \u001b[0m\r\r\n\u001b[1B\u001b[1B\u001b[1B\u001b[1B\u001b[1B\u001b[1B\u001b[1B\u001b[1B\u001b[1B\u001b[1B\u001b[1B\u001b[1B\u001b[1B\u001b[1B\u001b[1B\u001b[1B\u001b[1B\u001b[1B\u001b[1B\u001b[1B\u001b[1B\u001b[1B\u001b[1B\u001b[26;0H" ]
[ 21.28517, "o", "\u001b[1A\u001b[1A\u001b[1A\u001b[1A\u001b[1A\u001b[1A\u001b[1A\u001b[1A\u001b[1A\u001b[1A\u001b[1A\u001b[1A\u001b[1A\u001b[1A\u001b[1A\u001b[1A\u001b[1A\u001b[1A\u001b[1A\u001b[1A\u001b[1A\u001b[1A\u001b[1A\u001b[1A\u001b[2K\u001b[1A\u001b[100D\u001b[2K\r\r\n \\ \u001b[1;;m Glow \u001b[0m\r\r\n\u001b[1B\u001b[1B\u001b[1B\u001b[1B\u001b[1B\u001b[1B\u001b[1B\u001b[1B\u001b[1B\u001b[1B\u001b[1B\u001b[1B\u001b[1B\u001b[1B\u001b[1B\u001b[1B\u001b[1B\u001b[1B\u001b[1B\u001b[1B\u001b[1B\u001b[1B\u001b[1B\u001b[26;0H" ]
[ 21.38573, "o", "\u001b[1A\u001b[1A\u001b[1A\u001b[1A\u001b[1A\u001b[1A\u001b[1A\u001b[1A\u001b[1A\u001b[1A\u001b[1A\u001b[1A\u001b[1A\u001b[1A\u001b[1A\u001b[1A\u001b[1A\u001b[1A\u001b[1A\u001b[1A\u001b[1A\u001b[1A\u001b[1A\u001b[1A\u001b[2K\u001b[1A\u001b[100D\u001b[2K\r\r\n | \u001b[1;;m Glow \u001b[0m\r\r\n\u001b[1B\u001b[1B\u001b[1B\u001b[1B\u001b[1B\u001b[1B\u001b[1B\u001b[1B\u001b[1B\u001b[1B\u001b[1B\u001b[1B\u001b[1B\u001b[1B\u001b[1B\u001b[1B\u001b[1B\u001b[1B\u001b[1B\u001b[1B\u001b[1B\u001b[1B\u001b[1B\u001b[26;0H" ]
[ 21.50261, "o", "\u001b[1A\u001b[1A\u001b[1A\u001b[1A\u001b[1A\u001b[1A\u001b[1A\u001b[1A\u001b[1A\u001b[1A\u001b[1A\u001b[1A\u001b[1A\u001b[1A\u001b[1A\u001b[1A\u001b[1A\u001b[1A\u001b[1A\u001b[1A\u001b[1A\u001b[1A\u001b[1A\u001b[1A\u001b[2K\u001b[1A\u001b[100D\u001b[2K\r\r\n / \u001b[1;;m Glow \u001b[0m\r\r\n\u001b[1B\u001b[1B\u001b[1B\u001b[1B\u001b[1B\u001b[1B\u001b[1B\u001b[1B\u001b[1B\u001b[1B\u001b[1B\u001b[1B\u001b[1B\u001b[1B\u001b[1B\u001b[1B\u001b[1B\u001b[1B\u001b[1B\u001b[1B\u001b[1B\u001b[1B\u001b[1B\u001b[26;0H" ]
[ 21.60204, "o", "\u001b[1A\u001b[1A\u001b[1A\u001b[1A\u001b[1A\u001b[1A\u001b[1A\u001b[1A\u001b[1A\u001b[1A\u001b[1A\u001b[1A\u001b[1A\u001b[1A\u001b[1A\u001b[1A\u001b[1A\u001b[1A\u001b[1A\u001b[1A\u001b[1A\u001b[1A\u001b[1A\u001b[1A\u001b[2K\u001b[1A\u001b[100D\u001b[2K\r\r\n - \u001b[1;;m Glow \u001b[0m\r\r\n\u001b[1B\u001b[1B\u001b[1B\u001b[1B\u001b[1B\u001b[1B\u001b[1B\u001b[1B\u001b[1B\u001b[1B\u001b[1B\u001b[1B\u001b[1B\u001b[1B\u001b[1B\u001b[1B\u001b[1B\u001b[1B\u001b[1B\u001b[1B\u001b[1B\u001b[1B\u001b[1B\u001b[26;0H" ]
[ 21.70275, "o", "\u001b[1A\u001b[1A\u001b[1A\u001b[1A\u001b[1A\u001b[1A\u001b[1A\u001b[1A\u001b[1A\u001b[1A\u001b[1A\u001b[1A\u001b[1A\u001b[1A\u001b[1A\u001b[1A\u001b[1A\u001b[1A\u001b[1A\u001b[1A\u001b[1A\u001b[1A\u001b[1A\u001b[1A\u001b[2K\u001b[1A\u001b[100D\u001b[2K\r\r\n \\ \u001b[1;;m Glow \u001b[0m\r\r\n\u001b[1B\u001b[1B\u001b[1B\u001b[1B\u001b[1B\u001b[1B\u001b[1B\u001b[1B\u001b[1B\u001b[1B\u001b[1B\u001b[1B\u001b[1B\u001b[1B\u001b[1B\u001b[1B\u001b[1B\u001b[1B\u001b[1B\u001b[1B\u001b[1B\u001b[1B\u001b[1B\u001b[26;0H" ]
[ 21.80241, "o", "\u001b[1A\u001b[1A\u001b[1A\u001b[1A\u001b[1A\u001b[1A\u001b[1A\u001b[1A\u001b[1A\u001b[1A\u001b[1A\u001b[1A\u001b[1A\u001b[1A\u001b[1A\u001b[1A\u001b[1A\u001b[1A\u001b[1A\u001b[1A\u001b[1A\u001b[1A\u001b[1A\u001b[1A\u001b[2K\u001b[1A\u001b[100D\u001b[2K\r\r\n | \u001b[1;;m Glow \u001b[0m\r\r\n\u001b[1B\u001b[1B\u001b[1B\u001b[1B\u001b[1B\u001b[1B\u001b[1B\u001b[1B\u001b[1B\u001b[1B\u001b[1B\u001b[1B\u001b[1B\u001b[1B\u001b[1B\u001b[1B\u001b[1B\u001b[1B\u001b[1B\u001b[1B\u001b[1B\u001b[1B\u001b[1B\u001b[26;0H" ]
[ 21.90218, "o", "\u001b[1A\u001b[1A\u001b[1A\u001b[1A\u001b[1A\u001b[1A\u001b[1A\u001b[1A\u001b[1A\u001b[1A\u001b[1A\u001b[1A\u001b[1A\u001b[1A\u001b[1A\u001b[1A\u001b[1A\u001b[1A\u001b[1A\u001b[1A\u001b[1A\u001b[1A\u001b[1A\u001b[1A\u001b[2K\u001b[1A\u001b[100D\u001b[2K\r\r\n / \u001b[1;;m Glow \u001b[0m\r\r\n\u001b[1B\u001b[1B\u001b[1B\u001b[1B\u001b[1B\u001b[1B\u001b[1B\u001b[1B\u001b[1B\u001b[1B\u001b[1B\u001b[1B\u001b[1B\u001b[1B\u001b[1B\u001b[1B\u001b[1B\u001b[1B\u001b[1B\u001b[1B\u001b[1B\u001b[1B\u001b[1B\u001b[26;0H" ]
[ 22.00182, "o", "\u001b[1A\u001b[1A\u001b[1A\u001b[1A\u001b[1A\u001b[1A\u001b[1A\u001b[1A\u001b[1A\u001b[1A\u001b[1A\u001b[1A\u001b[1A\u001b[1A\u001b[1A\u001b[1A\u001b[1A\u001b[1A\u001b[1A\u001b[1A\u001b[1A\u001b[1A\u001b[1A\u001b[1A\u001b[2K\u001b[1A\u001b[100D\u001b[2K\r\r\n - \u001b[1;;m Glow \u001b[0m\r\r\n\u001b[1B\u001b[1B\u001b[1B\u001b[1B\u001b[1B\u001b[1B\u001b[1B\u001b[1B\u001b[1B\u001b[1B\u001b[1B\u001b[1B\u001b[1B\u001b[1B\u001b[1B\u001b[1B\u001b[1B\u001b[1B\u001b[1B\u001b[1B\u001b[1B\u001b[1B\u001b[1B\u001b[26;0H" ]
[ 22.10236, "o", "\u001b[1A\u001b[1A\u001b[1A\u001b[1A\u001b[1A\u001b[1A\u001b[1A\u001b[1A\u001b[1A\u001b[1A\u001b[1A\u001b[1A\u001b[1A\u001b[1A\u001b[1A\u001b[1A\u001b[1A\u001b[1A\u001b[1A\u001b[1A\u001b[1A\u001b[1A\u001b[1A\u001b[1A\u001b[2K\u001b[1A\u001b[100D\u001b[2K\r\r\n \\ \u001b[1;;m Glow \u001b[0m\r\r\n\u001b[1B\u001b[1B\u001b[1B\u001b[1B\u001b[1B\u001b[1B\u001b[1B\u001b[1B\u001b[1B\u001b[1B\u001b[1B\u001b[1B\u001b[1B\u001b[1B\u001b[1B\u001b[1B\u001b[1B\u001b[1B\u001b[1B\u001b[1B\u001b[1B\u001b[1B\u001b[1B\u001b[26;0H" ]
[ 22.20222, "o", "\u001b[1A\u001b[1A\u001b[1A\u001b[1A\u001b[1A\u001b[1A\u001b[1A\u001b[1A\u001b[1A\u001b[1A\u001b[1A\u001b[1A\u001b[1A\u001b[1A\u001b[1A\u001b[1A\u001b[1A\u001b[1A\u001b[1A\u001b[1A\u001b[1A\u001b[1A\u001b[1A\u001b[1A\u001b[2K\u001b[1A\u001b[100D\u001b[2K\r\r\n | \u001b[1;;m Glow \u001b[0m\r\r\n\u001b[1B\u001b[1B\u001b[1B\u001b[1B\u001b[1B\u001b[1B\u001b[1B\u001b[1B\u001b[1B\u001b[1B\u001b[1B\u001b[1B\u001b[1B\u001b[1B\u001b[1B\u001b[1B\u001b[1B\u001b[1B\u001b[1B\u001b[1B\u001b[1B\u001b[1B\u001b[1B\u001b[26;0H" ]
[ 22.30204, "o", "\u001b[1A\u001b[1A\u001b[1A\u001b[1A\u001b[1A\u001b[1A\u001b[1A\u001b[1A\u001b[1A\u001b[1A\u001b[1A\u001b[1A\u001b[1A\u001b[1A\u001b[1A\u001b[1A\u001b[1A\u001b[1A\u001b[1A\u001b[1A\u001b[1A\u001b[1A\u001b[1A\u001b[1A\u001b[2K\u001b[1A\u001b[100D\u001b[2K\r\r\n / \u001b[1;;m Glow \u001b[0m\r\r\n\u001b[1B\u001b[1B\u001b[1B\u001b[1B\u001b[1B\u001b[1B\u001b[1B\u001b[1B\u001b[1B\u001b[1B\u001b[1B\u001b[1B\u001b[1B\u001b[1B\u001b[1B\u001b[1B\u001b[1B\u001b[1B\u001b[1B\u001b[1B\u001b[1B\u001b[1B\u001b[1B\u001b[26;0H" ]
[ 22.40274, "o", "\u001b[1A\u001b[1A\u001b[1A\u001b[1A\u001b[1A\u001b[1A\u001b[1A\u001b[1A\u001b[1A\u001b[1A\u001b[1A\u001b[1A\u001b[1A\u001b[1A\u001b[1A\u001b[1A\u001b[1A\u001b[1A\u001b[1A\u001b[1A\u001b[1A\u001b[1A\u001b[1A\u001b[1A\u001b[2K\u001b[1A\u001b[100D\u001b[2K\r\r\n - \u001b[1;;m Glow \u001b[0m\r\r\n\u001b[1B\u001b[1B\u001b[1B\u001b[1B\u001b[1B\u001b[1B\u001b[1B\u001b[1B\u001b[1B\u001b[1B\u001b[1B\u001b[1B\u001b[1B\u001b[1B\u001b[1B\u001b[1B\u001b[1B\u001b[1B\u001b[1B\u001b[1B\u001b[1B\u001b[1B\u001b[1B\u001b[26;0H" ]
[ 22.44901, "o", "\u001b[1A\u001b[2K\u001b[1A\u001b[2K\u001b[1A\u001b[2K\u001b[1A\u001b[2K\u001b[1A\u001b[2K\u001b[1A\u001b[2K\u001b[1A\u001b[2K\u001b[1A\u001b[2K\u001b[1A\u001b[2K\u001b[1A\u001b[2K\u001b[1A\u001b[2K\u001b[1A\u001b[2K\u001b[1A\u001b[2K\u001b[1A\u001b[2K\u001b[1A\u001b[2K\u001b[1A\u001b[2K\u001b[1A\u001b[2K\u001b[1A\u001b[2K\u001b[1A\u001b[2K\u001b[1A\u001b[2K\u001b[1A\u001b[2K\u001b[1A\u001b[2K\u001b[1A\u001b[2K\u001b[1A\u001b[2K\u001b[1A\u001b[2K\u001b[1A\u001b[26;0H\u001b[0;25r\u001b[0;0H\u001b[19L\r\r\n\u001b[38;5;228;48;5;63;1m\u001b[0m\u001b[38;5;228;48;5;63;1m\u001b[0m  \u001b[38;5;228;48;5;63;1m \u001b[0m\u001b[38;5;228;48;5;63;1mGlow\u001b[0m\u001b[38;5;228;48;5;63;1m \u001b[0m\u001b[38;5;252m\u001b[38;5;252m \u001b[0m\u001b[38;5;252m \u001b[0m\u001b[38;5;252m \u001b[0m\u001b[38;5;252m \u001b[0m\u001b[38;5;252m \u001b[0m\u001b[38;5;252m \u001b[0m\u001b[38;5;252m \u001b[0m\u001b[38;5;252m \u001b[0m\u001b[38;5;252m \u001b[0m\u001b[38;5;252m \u001b[0m\u001b[38;5;252m \u001b[0m\u001b[38;5;252m \u001b[0m\u001b[38;5;252m \u001b[0m\u001b[38;5;252m \u001b[0m\u001b[38;5;252m \u001b[0m\u001b[38;5;252m \u001b[0m\u001b[38;5;252m \u001b[0m\u001b[38;5;252m \u001b[0m\u001b[38;5;252m \u001b[0m\u001b[38;5;252m \u001b[0m\u001b[38;5;252m \u001b[0m\u001b[38;5;252m \u001b[0m\u001b[38;5;252m \u001b[0m\u001b[38;5;252m \u001b[0m\u001b[38;5;252m \u001b[0m\u001b[38;5;252m \u001b[0m\u001b[38;5;252m \u001b[0m\u001b[38;5;252m \u001b[0m\u001b[38;5;252m \u001b[0m\u001b[38;5;252m \u001b[0m\u001b[38;5;252m \u001b[0m\u001b[38;5;252m \u001b[0m\u001b[38;5;252m \u001b[0m\u001b[38;5;252m \u001b[0m\u001b[38;5;252m \u001b[0m\u001b[38;5;252m \u001b[0m\u001b[38;5;252m \u001b[0m\u001b[38;5;252m \u001b[0m\u001b[38;5;252m \u001b[0m\u001b[38;5;252m \u001b[0m\u001b[38;5;2" ]
[ 22.44918, "o", "52m \u001b[0m\u001b[38;5;252m \u001b[0m\u001b[38;5;252m \u001b[0m\u001b[38;5;252m \u001b[0m\u001b[38;5;252m \u001b[0m\u001b[38;5;252m \u001b[0m\u001b[38;5;252m \u001b[0m\u001b[38;5;252m \u001b[0m\u001b[38;5;252m \u001b[0m\u001b[38;5;252m \u001b[0m\u001b[38;5;252m \u001b[0m\u001b[38;5;252m \u001b[0m\u001b[38;5;252m \u001b[0m\u001b[38;5;252m \u001b[0m\u001b[38;5;252m \u001b[0m\u001b[38;5;252m \u001b[0m\u001b[38;5;252m \u001b[0m\u001b[38;5;252m \u001b[0m\u001b[38;5;252m \u001b[0m\u001b[38;5;252m \u001b[0m\u001b[38;5;252m \u001b[0m\u001b[38;5;252m \u001b[0m\u001b[38;5;252m \u001b[0m\u001b[38;5;252m \u001b[0m\u001b[38;5;252m \u001b[0m\u001b[38;5;252m \u001b[0m\u001b[38;5;252m \u001b[0m\u001b[38;5;252m \u001b[0m\u001b[38;5;252m \u001b[0m\u001b[38;5;252m \u001b[0m\u001b[38;5;252m \u001b[0m\u001b[38;5;252m \u001b[0m\u001b[38;5;252m \u001b[0m\u001b[38;5;252m \u001b[0m\u001b[38;5;252m \u001b[0m\u001b[38;5;252m \u001b[0m\u001b[38;5;252m \u001b[0m\u001b[38;5;252m \u001b[0m\u001b[38;5;252m \u001b[0m\u001b[38;5;252m \u001b[0m\u001b[38;5;252m \u001b[0m\u001b[38;5;252m \u001b[0m\u001b[38;5;252m \u001b[0m\u001b[38;5;252m \u001b[0m\u001b[38;5;252m \u001b[0m\u001b[38;5;252m \u001b[0m\u001b[38;5;252m \u001b[0m\u001b[38;5;252m \u001b[0m\u001b[38;5;252m \u001b[0m\u001b[38;5;252m \u001b[0m\u001b[0m\r\r\n\u001b[0m  \u001b[38;5;252m \u001b[0m\u001b[38;5;252m \u001b[0m\u001b[38;5;252m \u001b[0m\u001b[38;5;252m \u001b[0m\u001b[38;5;252m \u001b[0m\u001b[38;5;252m \u001b[0m\u001b[38;5;252m \u001b[0m\u001b[38;5;252m \u001b[0m\u001b[38;5;252m \u001b[0m\u001b[38;5;252m \u001b[0m\u001b[38;5;252m \u001b[0m\u001b[38;5;252m \u001b[0m\u001b[38;5;252m \u001b[0m\u001b[38;5;252m" ]
[ 22.44932, "o", " \u001b[0m\u001b[38;5;252m \u001b[0m\u001b[38;5;252m \u001b[0m\u001b[38;5;252m \u001b[0m\u001b[38;5;252m \u001b[0m\u001b[38;5;252m \u001b[0m\u001b[38;5;252m \u001b[0m\u001b[38;5;252m \u001b[0m\u001b[38;5;252m \u001b[0m\u001b[38;5;252m \u001b[0m\u001b[38;5;252m \u001b[0m\u001b[38;5;252m \u001b[0m\u001b[38;5;252m \u001b[0m\u001b[38;5;252m \u001b[0m\u001b[38;5;252m \u001b[0m\u001b[38;5;252m \u001b[0m\u001b[38;5;252m \u001b[0m\u001b[38;5;252m \u001b[0m\u001b[38;5;252m \u001b[0m\u001b[38;5;252m \u001b[0m\u001b[38;5;252m \u001b[0m\u001b[38;5;252m \u001b[0m\u001b[38;5;252m \u001b[0m\u001b[38;5;252m \u001b[0m\u001b[38;5;252m \u001b[0m\u001b[38;5;252m \u001b[0m\u001b[38;5;252m \u001b[0m\u001b[38;5;252m \u001b[0m\u001b[38;5;252m \u001b[0m\u001b[38;5;252m \u001b[0m\u001b[38;5;252m \u001b[0m\u001b[38;5;252m \u001b[0m\u001b[38;5;252m \u001b[0m\u001b[38;5;252m \u001b[0m\u001b[38;5;252m \u001b[0m\u001b[38;5;252m \u001b[0m\u001b[38;5;252m \u001b[0m\u001b[38;5;252m \u001b[0m\u001b[38;5;252m \u001b[0m\u001b[38;5;252m \u001b[0m\u001b[38;5;252m \u001b[0m\u001b[38;5;252m \u001b[0m\u001b[38;5;252m \u001b[0m\u001b[38;5;252m \u001b[0m\u001b[38;5;252m \u001b[0m\u001b[38;5;252m \u001b[0m\u001b[38;5;252m \u001b[0m\u001b[38;5;252m \u001b[0m\u001b[38;5;252m \u001b[0m\u001b[38;5;252m \u001b[0m\u001b[38;5;252m \u001b[0m\u001b[38;5;252m \u001b[0m\u001b[38;5;252m \u001b[0m\u001b[38;5;252m \u001b[0m\u001b[38;5;252m \u001b[0m\u001b[38;5;252m \u001b[0m\u001b[38;5;252m \u001b[0m\u001b[38;5;252m \u001b[0m\u001b[38;5;252m \u001b[0m\u001b[38;5;252m \u001b[0m\u001b[38;5;252m \u001b[0m\u001b[38;5;252m \u001b[0m\u001b[38;5;252m \u001b[0m\u001b[38;5;252m \u001b[0m\u001b[38;5;252m" ]
[ 22.44964, "o", " \u001b[0m\u001b[38;5;252m \u001b[0m\u001b[38;5;252m \u001b[0m\u001b[38;5;252m \u001b[0m\u001b[38;5;252m \u001b[0m\u001b[38;5;252m \u001b[0m\u001b[38;5;252m \u001b[0m\u001b[38;5;252m \u001b[0m\u001b[38;5;252m \u001b[0m\u001b[38;5;252m \u001b[0m\u001b[38;5;252m \u001b[0m\u001b[38;5;252m \u001b[0m\u001b[38;5;252m \u001b[0m\u001b[38;5;252m \u001b[0m\u001b[38;5;252m \u001b[0m\u001b[38;5;252m \u001b[0m\u001b[38;5;252m \u001b[0m\u001b[38;5;252m \u001b[0m\u001b[38;5;252m \u001b[0m\r\r\n\u001b[38;5;252m\u001b[0m\u001b[38;5;252m\u001b[0m  \u001b[38;5;252mRender markdown on the CLI, with \u001b[0m\u001b[38;5;252;3mpizzazz\u001b[0m\u001b[38;5;252m!\u001b[0m\u001b[38;5;252m \u001b[0m\u001b[38;5;252m \u001b[0m\u001b[38;5;252m \u001b[0m\u001b[38;5;252m \u001b[0m\u001b[38;5;252m \u001b[0m\u001b[38;5;252m \u001b[0m\u001b[38;5;252m \u001b[0m\u001b[38;5;252m \u001b[0m\u001b[38;5;252m \u001b[0m\u001b[38;5;252m \u001b[0m\u001b[38;5;252m \u001b[0m\u001b[38;5;252m \u001b[0m\u001b[38;5;252m \u001b[0m\u001b[38;5;252m \u001b[0m\u001b[38;5;252m \u001b[0m\u001b[38;5;252m \u001b[0m\u001b[38;5;252m \u001b[0m\u001b[38;5;252m \u001b[0m\u001b[38;5;252m \u001b[0m\u001b[38;5;252m \u001b[0m\u001b[38;5;252m \u001b[0m\u001b[38;5;252m \u001b[0m\u001b[38;5;252m \u001b[0m\u001b[38;5;252m \u001b[0m\u001b[38;5;252m \u001b[0m\u001b[38;5;252m \u001b[0m\u001b[38;5;252m \u001b[0m\u001b[38;5;252m \u001b[0m\u001b[38;5;252m \u001b[0m\u001b[38;5;252m \u001b[0m\u001b[38;5;252m \u001b[0m\u001b[38;5;252m \u001b[0m\u001b[38;5;252m \u001b[0m\u001b[38;5;252m \u001b[0m\u001b[38;5;252m \u001b[0m\u001b[38;5;252m \u001b[0m\u001b[38;5;252m \u001b[0m\u001b[38;5;252m \u001b[0m" ]
[ 22.44968, "o", "\u001b[38;5;252m \u001b[0m\u001b[38;5;252m \u001b[0m\u001b[38;5;252m \u001b[0m\u001b[38;5;252m \u001b[0m\u001b[38;5;252m \u001b[0m\u001b[38;5;252m \u001b[0m\u001b[38;5;252m \u001b[0m\u001b[38;5;252m \u001b[0m\u001b[38;5;252m \u001b[0m\u001b[38;5;252m \u001b[0m\u001b[38;5;252m \u001b[0m\u001b[38;5;252m \u001b[0m\u001b[38;5;252m \u001b[0m\u001b[38;5;252m \u001b[0m\u001b[38;5;252m \u001b[0m\u001b[38;5;252m \u001b[0m\u001b[38;5;252m \u001b[0m\r\r\n\u001b[38;5;252m\u001b[0m  \u001b[38;5;252m\u001b[38;5;252m \u001b[0m\u001b[38;5;252m \u001b[0m\u001b[38;5;252m \u001b[0m\u001b[38;5;252m \u001b[0m\u001b[38;5;252m \u001b[0m\u001b[38;5;252m \u001b[0m\u001b[38;5;252m \u001b[0m\u001b[38;5;252m \u001b[0m\u001b[38;5;252m \u001b[0m\u001b[38;5;252m \u001b[0m\u001b[38;5;252m \u001b[0m\u001b[38;5;252m \u001b[0m\u001b[38;5;252m \u001b[0m\u001b[38;5;252m \u001b[0m\u001b[38;5;252m \u001b[0m\u001b[38;5;252m \u001b[0m\u001b[38;5;252m \u001b[0m\u001b[38;5;252m \u001b[0m\u001b[38;5;252m \u001b[0m\u001b[38;5;252m \u001b[0m\u001b[38;5;252m \u001b[0m\u001b[38;5;252m \u001b[0m\u001b[38;5;252m \u001b[0m\u001b[38;5;252m \u001b[0m\u001b[38;5;252m \u001b[0m\u001b[38;5;252m \u001b[0m\u001b[38;5;252m \u001b[0m\u001b[38;5;252m \u001b[0m\u001b[38;5;252m \u001b[0m\u001b[38;5;252m \u001b[0m\u001b[38;5;252m \u001b[0m\u001b[38;5;252m \u001b[0m\u001b[38;5;252m \u001b[0m\u001b[38;5;252m \u001b[0m\u001b[38;5;252m \u001b[0m\u001b[38;5;252m \u001b[0m\u001b[38;5;252m \u001b[0m\u001b[38;5;252m \u001b[0m\u001b[38;5;252m \u001b[0m\u001b[38;5;252m \u001b[0m\u001b[38;5;252m \u001b[0m\u001b[38;5;252m \u001b[0m\u001b[38;5;252m \u001b[0m\u001b[38;5;252m \u001b[0m\u001b[38;5;252m \u001b[0m\u001b" ]
[ 22.44971, "o", "[38;5;252m \u001b[0m\u001b[38;5;252m \u001b[0m\u001b[38;5;252m \u001b[0m\u001b[38;5;252m \u001b[0m\u001b[38;5;252m \u001b[0m\u001b[38;5;252m \u001b[0m\u001b[38;5;252m \u001b[0m\u001b[38;5;252m \u001b[0m\u001b[38;5;252m \u001b[0m\u001b[38;5;252m \u001b[0m\u001b[38;5;252m \u001b[0m\u001b[38;5;252m \u001b[0m\u001b[38;5;252m \u001b[0m\u001b[38;5;252m \u001b[0m\u001b[38;5;252m \u001b[0m\u001b[38;5;252m \u001b[0m\u001b[38;5;252m \u001b[0m\u001b[38;5;252m \u001b[0m\u001b[38;5;252m \u001b[0m\u001b[38;5;252m \u001b[0m\u001b[38;5;252m \u001b[0m\u001b[38;5;252m \u001b[0m\u001b[38;5;252m \u001b[0m\u001b[38;5;252m \u001b[0m\u001b[38;5;252m \u001b[0m\u001b[38;5;252m \u001b[0m\u001b[38;5;252m \u001b[0m\u001b[38;5;252m \u001b[0m\u001b[38;5;252m \u001b[0m\u001b[38;5;252m \u001b[0m\u001b[38;5;252m \u001b[0m\u001b[38;5;252m \u001b[0m\u001b[38;5;252m \u001b[0m\u001b[38;5;252m \u001b[0m\u001b[38;5;252m \u001b[0m\u001b[38;5;252m \u001b[0m\u001b[38;5;252m \u001b[0m\u001b[38;5;252m \u001b[0m\u001b[38;5;252m \u001b[0m\u001b[38;5;252m \u001b[0m\u001b[38;5;252m \u001b[0m\u001b[38;5;252m \u001b[0m\u001b[38;5;252m \u001b[0m\u001b[38;5;252m \u001b[0m\u001b[38;5;252m \u001b[0m\u001b[38;5;252m \u001b[0m\u001b[38;5;252m \u001b[0m\u001b[38;5;252m \u001b[0m\u001b[38;5;252m \u001b[0m\u001b[38;5;252m \u001b[0m\u001b[38;5;252m \u001b[0m\u001b[0m\r\r\n\u001b[0m\u001b[38;5;39;1m\u001b[0m\u001b[38;5;39;1m\u001b[0m  \u001b[38;5;39;1m## \u001b[0m\u001b[38;5;39;1mWhat is\u001b[0m\u001b[38;5;39;1m it?\u001b[0m\u001b[38;5;252m\u001b[38;5;252m \u001b[0m\u001b[38;5;252m \u001b[0m\u001b[38;5;252m \u001b[0m\u001b[38;5;252m \u001b[0m\u001b[38;5;252m \u001b[0m\u001b[38;5;252m" ]
[ 22.44975, "o", " \u001b[0m\u001b[38;5;252m \u001b[0m\u001b[38;5;252m \u001b[0m\u001b[38;5;252m \u001b[0m\u001b[38;5;252m \u001b[0m\u001b[38;5;252m \u001b[0m\u001b[38;5;252m \u001b[0m\u001b[38;5;252m \u001b[0m\u001b[38;5;252m \u001b[0m\u001b[38;5;252m \u001b[0m\u001b[38;5;252m \u001b[0m\u001b[38;5;252m \u001b[0m\u001b[38;5;252m \u001b[0m\u001b[38;5;252m \u001b[0m\u001b[38;5;252m \u001b[0m\u001b[38;5;252m \u001b[0m\u001b[38;5;252m \u001b[0m\u001b[38;5;252m \u001b[0m\u001b[38;5;252m \u001b[0m\u001b[38;5;252m \u001b[0m\u001b[38;5;252m \u001b[0m\u001b[38;5;252m \u001b[0m\u001b[38;5;252m \u001b[0m\u001b[38;5;252m \u001b[0m\u001b[38;5;252m \u001b[0m\u001b[38;5;252m \u001b[0m\u001b[38;5;252m \u001b[0m\u001b[38;5;252m \u001b[0m\u001b[38;5;252m \u001b[0m\u001b[38;5;252m \u001b[0m\u001b[38;5;252m \u001b[0m\u001b[38;5;252m \u001b[0m\u001b[38;5;252m \u001b[0m\u001b[38;5;252m \u001b[0m\u001b[38;5;252m \u001b[0m\u001b[38;5;252m \u001b[0m\u001b[38;5;252m \u001b[0m\u001b[38;5;252m \u001b[0m\u001b[38;5;252m \u001b[0m\u001b[38;5;252m \u001b[0m\u001b[38;5;252m \u001b[0m\u001b[38;5;252m \u001b[0m\u001b[38;5;252m \u001b[0m\u001b[38;5;252m \u001b[0m\u001b[38;5;252m \u001b[0m\u001b[38;5;252m \u001b[0m\u001b[38;5;252m \u001b[0m\u001b[38;5;252m \u001b[0m\u001b[38;5;252m \u001b[0m\u001b[38;5;252m \u001b[0m\u001b[38;5;252m \u001b[0m\u001b[38;5;252m \u001b[0m\u001b[38;5;252m \u001b[0m\u001b[38;5;252m \u001b[0m\u001b[38;5;252m \u001b[0m\u001b[38;5;252m \u001b[0m\u001b[38;5;252m \u001b[0m\u001b[38;5;252m \u001b[0m\u001b[38;5;252m \u001b[0m\u001b[38;5;252m \u001b[0m\u001b[38;5;252m \u001b[0m\u001b[38;5;252m \u001b[0m\u001b[38;5;252m \u001b[0m\u001b[38;5;252m \u001b[0m\u001b[38;5;252m" ]
[ 22.44987, "o", " \u001b[0m\u001b[38;5;252m \u001b[0m\u001b[38;5;252m \u001b[0m\u001b[38;5;252m \u001b[0m\u001b[38;5;252m \u001b[0m\u001b[38;5;252m \u001b[0m\u001b[38;5;252m \u001b[0m\u001b[38;5;252m \u001b[0m\u001b[38;5;252m \u001b[0m\u001b[38;5;252m \u001b[0m\u001b[38;5;252m \u001b[0m\u001b[38;5;252m \u001b[0m\u001b[38;5;252m \u001b[0m\u001b[0m\r\r\n\u001b[0m  \u001b[38;5;252m \u001b[0m\u001b[38;5;252m \u001b[0m\u001b[38;5;252m \u001b[0m\u001b[38;5;252m \u001b[0m\u001b[38;5;252m \u001b[0m\u001b[38;5;252m \u001b[0m\u001b[38;5;252m \u001b[0m\u001b[38;5;252m \u001b[0m\u001b[38;5;252m \u001b[0m\u001b[38;5;252m \u001b[0m\u001b[38;5;252m \u001b[0m\u001b[38;5;252m \u001b[0m\u001b[38;5;252m \u001b[0m\u001b[38;5;252m \u001b[0m\u001b[38;5;252m \u001b[0m\u001b[38;5;252m \u001b[0m\u001b[38;5;252m \u001b[0m\u001b[38;5;252m \u001b[0m\u001b[38;5;252m \u001b[0m\u001b[38;5;252m \u001b[0m\u001b[38;5;252m \u001b[0m\u001b[38;5;252m \u001b[0m\u001b[38;5;252m \u001b[0m\u001b[38;5;252m \u001b[0m\u001b[38;5;252m \u001b[0m\u001b[38;5;252m \u001b[0m\u001b[38;5;252m \u001b[0m\u001b[38;5;252m \u001b[0m\u001b[38;5;252m \u001b[0m\u001b[38;5;252m \u001b[0m\u001b[38;5;252m \u001b[0m\u001b[38;5;252m \u001b[0m\u001b[38;5;252m \u001b[0m\u001b[38;5;252m \u001b[0m\u001b[38;5;252m \u001b[0m\u001b[38;5;252m \u001b[0m\u001b[38;5;252m \u001b[0m\u001b[38;5;252m \u001b[0m\u001b[38;5;252m \u001b[0m\u001b[38;5;252m \u001b[0m\u001b[38;5;252m \u001b[0m\u001b[38;5;252m \u001b[0m\u001b[38;5;252m \u001b[0m\u001b[38;5;252m \u001b[0m\u001b[38;5;252m \u001b[0m\u001b[38;5;252m \u001b[0m\u001b[38;5;252m \u001b[0m\u001b[38;5;252m \u001b[0m\u001b[38;5;252m \u001b[0m\u001b[38;5;252m \u001b[0m\u001b[38;5;252m \u001b[" ]
[ 22.44989, "o", "0m\u001b[38;5;252m \u001b[0m\u001b[38;5;252m \u001b[0m\u001b[38;5;252m \u001b[0m\u001b[38;5;252m \u001b[0m\u001b[38;5;252m \u001b[0m\u001b[38;5;252m \u001b[0m\u001b[38;5;252m \u001b[0m\u001b[38;5;252m \u001b[0m\u001b[38;5;252m \u001b[0m\u001b[38;5;252m \u001b[0m\u001b[38;5;252m \u001b[0m\u001b[38;5;252m \u001b[0m\u001b[38;5;252m \u001b[0m\u001b[38;5;252m \u001b[0m\u001b[38;5;252m \u001b[0m\u001b[38;5;252m \u001b[0m\u001b[38;5;252m \u001b[0m\u001b[38;5;252m \u001b[0m\u001b[38;5;252m \u001b[0m\u001b[38;5;252m \u001b[0m\u001b[38;5;252m \u001b[0m\u001b[38;5;252m \u001b[0m\u001b[38;5;252m \u001b[0m\u001b[38;5;252m \u001b[0m\u001b[38;5;252m \u001b[0m\u001b[38;5;252m \u001b[0m\u001b[38;5;252m \u001b[0m\u001b[38;5;252m \u001b[0m\u001b[38;5;252m \u001b[0m\u001b[38;5;252m \u001b[0m\u001b[38;5;252m \u001b[0m\u001b[38;5;252m \u001b[0m\u001b[38;5;252m \u001b[0m\u001b[38;5;252m \u001b[0m\u001b[38;5;252m \u001b[0m\u001b[38;5;252m \u001b[0m\u001b[38;5;252m \u001b[0m\u001b[38;5;252m \u001b[0m\u001b[38;5;252m \u001b[0m\u001b[38;5;252m \u001b[0m\u001b[38;5;252m \u001b[0m\u001b[38;5;252m \u001b[0m\u001b[38;5;252m \u001b[0m\u001b[38;5;252m \u001b[0m\u001b[38;5;252m \u001b[0m\r\r\n\u001b[38;5;252m\u001b[0m\u001b[38;5;252m\u001b[0m  \u001b[38;5;252mGlow is a terminal based markdown reader designed from the ground up to\u001b[0m\u001b[38;5;252m bring \u001b[0m\u001b[38;5;252mout the beauty—and\u001b[0m\r\r\n\u001b[0m\u001b[38;5;252m\u001b[0m  \u001b[38;5;252mpower—of the\u001b[0m\u001b[38;5;252m CLI.\u001b[0m\u001b[38;5;252m \u001b[0m\u001b[38;5;252m \u001b[0m\u001b[38;5;252m \u001b[0m\u001b[3" ]
[ 22.44990, "o", "8;5;252m \u001b[0m\u001b[38;5;252m \u001b[0m\u001b[38;5;252m \u001b[0m\u001b[38;5;252m \u001b[0m\u001b[38;5;252m \u001b[0m\u001b[38;5;252m \u001b[0m\u001b[38;5;252m \u001b[0m\u001b[38;5;252m \u001b[0m\u001b[38;5;252m \u001b[0m\u001b[38;5;252m \u001b[0m\u001b[38;5;252m \u001b[0m\u001b[38;5;252m \u001b[0m\u001b[38;5;252m \u001b[0m\u001b[38;5;252m \u001b[0m\u001b[38;5;252m \u001b[0m\u001b[38;5;252m \u001b[0m\u001b[38;5;252m \u001b[0m\u001b[38;5;252m \u001b[0m\u001b[38;5;252m \u001b[0m\u001b[38;5;252m \u001b[0m\u001b[38;5;252m \u001b[0m\u001b[38;5;252m \u001b[0m\u001b[38;5;252m \u001b[0m\u001b[38;5;252m \u001b[0m\u001b[38;5;252m \u001b[0m\u001b[38;5;252m \u001b[0m\u001b[38;5;252m \u001b[0m\u001b[38;5;252m \u001b[0m\u001b[38;5;252m \u001b[0m\u001b[38;5;252m \u001b[0m\u001b[38;5;252m \u001b[0m\u001b[38;5;252m \u001b[0m\u001b[38;5;252m \u001b[0m\u001b[38;5;252m \u001b[0m\u001b[38;5;252m \u001b[0m\u001b[38;5;252m \u001b[0m\u001b[38;5;252m \u001b[0m\u001b[38;5;252m \u001b[0m\u001b[38;5;252m \u001b[0m\u001b[38;5;252m \u001b[0m\u001b[38;5;252m \u001b[0m\u001b[38;5;252m \u001b[0m\u001b[38;5;252m \u001b[0m\u001b[38;5;252m \u001b[0m\u001b[38;5;252m \u001b[0m\u001b[38;5;252m \u001b[0m\u001b[38;5;252m \u001b[0m\u001b[38;5;252m \u001b[0m\u001b[38;5;252m \u001b[0m\u001b[38;5;252m \u001b[0m\u001b[38;5;252m \u001b[0m\u001b[38;5;252m \u001b[0m\u001b[38;5;252m \u001b[0m\u001b[38;5;252m \u001b[0m\u001b[38;5;252m \u001b[0m\u001b[38;5;252m \u001b[0m\u001b[38;5;252m \u001b[0m\u001b[38;5;252m \u001b[0m\u001b[38;5;252m \u001b[0m\u001b[38;5;252m \u001b[0m\u001b[38;5;252m \u001b[0m\u001b[38;5;252m \u001b[0m\u001b[38;5;252m \u001b[0m\u001b[38;5;252m \u001b[0m\u001b[3" ]
[ 22.44992, "o", "8;5;252m \u001b[0m\u001b[38;5;252m \u001b[0m\u001b[38;5;252m \u001b[0m\u001b[38;5;252m \u001b[0m\u001b[38;5;252m \u001b[0m\u001b[38;5;252m \u001b[0m\u001b[38;5;252m \u001b[0m\u001b[38;5;252m \u001b[0m\u001b[38;5;252m \u001b[0m\u001b[38;5;252m \u001b[0m\u001b[38;5;252m \u001b[0m\u001b[38;5;252m \u001b[0m\r\r\n\u001b[38;5;252m\u001b[0m  \u001b[38;5;252m\u001b[38;5;252m \u001b[0m\u001b[38;5;252m \u001b[0m\u001b[38;5;252m \u001b[0m\u001b[38;5;252m \u001b[0m\u001b[38;5;252m \u001b[0m\u001b[38;5;252m \u001b[0m\u001b[38;5;252m \u001b[0m\u001b[38;5;252m \u001b[0m\u001b[38;5;252m \u001b[0m\u001b[38;5;252m \u001b[0m\u001b[38;5;252m \u001b[0m\u001b[38;5;252m \u001b[0m\u001b[38;5;252m \u001b[0m\u001b[38;5;252m \u001b[0m\u001b[38;5;252m \u001b[0m\u001b[38;5;252m \u001b[0m\u001b[38;5;252m \u001b[0m\u001b[38;5;252m \u001b[0m\u001b[38;5;252m \u001b[0m\u001b[38;5;252m \u001b[0m\u001b[38;5;252m \u001b[0m\u001b[38;5;252m \u001b[0m\u001b[38;5;252m \u001b[0m\u001b[38;5;252m \u001b[0m\u001b[38;5;252m \u001b[0m\u001b[38;5;252m \u001b[0m\u001b[38;5;252m \u001b[0m\u001b[38;5;252m \u001b[0m\u001b[38;5;252m \u001b[0m\u001b[38;5;252m \u001b[0m\u001b[38;5;252m \u001b[0m\u001b[38;5;252m \u001b[0m\u001b[38;5;252m \u001b[0m\u001b[38;5;252m \u001b[0m\u001b[38;5;252m \u001b[0m\u001b[38;5;252m \u001b[0m\u001b[38;5;252m \u001b[0m\u001b[38;5;252m \u001b[0m\u001b[38;5;252m \u001b[0m\u001b[38;5;252m \u001b[0m\u001b[38;5;252m \u001b[0m\u001b[38;5;252m \u001b[0m\u001b[38;5;252m \u001b[0m\u001b[38;5;252m \u001b[0m\u001b[38;5;252m \u001b[0m\u001b[38;5;252m \u001b[0m\u001b[38;5;252m \u001b[0m\u001b[38;5;252m \u001b[0m\u001b[38;5;252m \u001b[0m\u001b[38;5;252m \u001b[0m\u001b[38" ]
[ 22.44993, "o", ";5;252m \u001b[0m\u001b[38;5;252m \u001b[0m\u001b[38;5;252m \u001b[0m\u001b[38;5;252m \u001b[0m\u001b[38;5;252m \u001b[0m\u001b[38;5;252m \u001b[0m\u001b[38;5;252m \u001b[0m\u001b[38;5;252m \u001b[0m\u001b[38;5;252m \u001b[0m\u001b[38;5;252m \u001b[0m\u001b[38;5;252m \u001b[0m\u001b[38;5;252m \u001b[0m\u001b[38;5;252m \u001b[0m\u001b[38;5;252m \u001b[0m\u001b[38;5;252m \u001b[0m\u001b[38;5;252m \u001b[0m\u001b[38;5;252m \u001b[0m\u001b[38;5;252m \u001b[0m\u001b[38;5;252m \u001b[0m\u001b[38;5;252m \u001b[0m\u001b[38;5;252m \u001b[0m\u001b[38;5;252m \u001b[0m\u001b[38;5;252m \u001b[0m\u001b[38;5;252m \u001b[0m\u001b[38;5;252m \u001b[0m\u001b[38;5;252m \u001b[0m\u001b[38;5;252m \u001b[0m\u001b[38;5;252m \u001b[0m\u001b[38;5;252m \u001b[0m\u001b[38;5;252m \u001b[0m\u001b[38;5;252m \u001b[0m\u001b[38;5;252m \u001b[0m\u001b[38;5;252m \u001b[0m\u001b[38;5;252m \u001b[0m\u001b[38;5;252m \u001b[0m\u001b[38;5;252m \u001b[0m\u001b[38;5;252m \u001b[0m\u001b[38;5;252m \u001b[0m\u001b[38;5;252m \u001b[0m\u001b[38;5;252m \u001b[0m\u001b[38;5;252m \u001b[0m\u001b[38;5;252m \u001b[0m\u001b[38;5;252m \u001b[0m\u001b[38;5;252m \u001b[0m\u001b[38;5;252m \u001b[0m\u001b[38;5;252m \u001b[0m\u001b[0m\r\r\n\u001b[0m\u001b[38;5;39;1m\u001b[0m\u001b[38;5;39;1m\u001b[0m  \u001b[38;5;39;1m## \u001b[0m\u001b[38;5;39;1mLicense\u001b[0m\u001b[38;5;252m\u001b[38;5;252m \u001b[0m\u001b[38;5;252m \u001b[0m\u001b[38;5;252m \u001b[0m\u001b[38;5;252m \u001b[0m\u001b[38;5;252m \u001b[0m\u001b[38;5;252m \u001b[0m\u001b[38;5;252m \u001b[0m\u001b[38;5;252m \u001b[0m\u001b[38;5;252m \u001b[0m\u001b[38;5;252m \u001b[0m\u001b[38;5;252m \u001b[0m\u001b[38;5;252m \u001b[0m\u001b[" ]
[ 22.45010, "o", "38;5;252m \u001b[0m\u001b[38;5;252m \u001b[0m\u001b[38;5;252m \u001b[0m\u001b[38;5;252m \u001b[0m\u001b[38;5;252m \u001b[0m\u001b[38;5;252m \u001b[0m\u001b[38;5;252m \u001b[0m\u001b[38;5;252m \u001b[0m\u001b[38;5;252m \u001b[0m\u001b[38;5;252m \u001b[0m\u001b[38;5;252m \u001b[0m\u001b[38;5;252m \u001b[0m\u001b[38;5;252m \u001b[0m\u001b[38;5;252m \u001b[0m\u001b[38;5;252m \u001b[0m\u001b[38;5;252m \u001b[0m\u001b[38;5;252m \u001b[0m\u001b[38;5;252m \u001b[0m\u001b[38;5;252m \u001b[0m\u001b[38;5;252m \u001b[0m\u001b[38;5;252m \u001b[0m\u001b[38;5;252m \u001b[0m\u001b[38;5;252m \u001b[0m\u001b[38;5;252m \u001b[0m\u001b[38;5;252m \u001b[0m\u001b[38;5;252m \u001b[0m\u001b[38;5;252m \u001b[0m\u001b[38;5;252m \u001b[0m\u001b[38;5;252m \u001b[0m\u001b[38;5;252m \u001b[0m\u001b[38;5;252m \u001b[0m\u001b[38;5;252m \u001b[0m\u001b[38;5;252m \u001b[0m\u001b[38;5;252m \u001b[0m\u001b[38;5;252m \u001b[0m\u001b[38;5;252m \u001b[0m\u001b[38;5;252m \u001b[0m\u001b[38;5;252m \u001b[0m\u001b[38;5;252m \u001b[0m\u001b[38;5;252m \u001b[0m\u001b[38;5;252m \u001b[0m\u001b[38;5;252m \u001b[0m\u001b[38;5;252m \u001b[0m\u001b[38;5;252m \u001b[0m\u001b[38;5;252m \u001b[0m\u001b[38;5;252m \u001b[0m\u001b[38;5;252m \u001b[0m\u001b[38;5;252m \u001b[0m\u001b[38;5;252m \u001b[0m\u001b[38;5;252m \u001b[0m\u001b[38;5;252m \u001b[0m\u001b[38;5;252m \u001b[0m\u001b[38;5;252m \u001b[0m\u001b[38;5;252m \u001b[0m\u001b[38;5;252m \u001b[0m\u001b[38;5;252m \u001b[0m\u001b[38;5;252m \u001b[0m\u001b[38;5;252m \u001b[0m\u001b[38;5;252m \u001b[0m\u001b[38;5;252m \u001b[0m\u001b[38;5;252m \u001b[0m\u001b[38;5;252m \u001b[0m\u001b[38;5;252m \u001b[0m\u001b[38;5;252m \u001b[0m\u001b[" ]
[ 22.45014, "o", "38;5;252m \u001b[0m\u001b[38;5;252m \u001b[0m\u001b[38;5;252m \u001b[0m\u001b[38;5;252m \u001b[0m\u001b[38;5;252m \u001b[0m\u001b[38;5;252m \u001b[0m\u001b[38;5;252m \u001b[0m\u001b[38;5;252m \u001b[0m\u001b[38;5;252m \u001b[0m\u001b[38;5;252m \u001b[0m\u001b[0m\r\r\n\u001b[0m  \u001b[38;5;252m \u001b[0m\u001b[38;5;252m \u001b[0m\u001b[38;5;252m \u001b[0m\u001b[38;5;252m \u001b[0m\u001b[38;5;252m \u001b[0m\u001b[38;5;252m \u001b[0m\u001b[38;5;252m \u001b[0m\u001b[38;5;252m \u001b[0m\u001b[38;5;252m \u001b[0m\u001b[38;5;252m \u001b[0m\u001b[38;5;252m \u001b[0m\u001b[38;5;252m \u001b[0m\u001b[38;5;252m \u001b[0m\u001b[38;5;252m \u001b[0m\u001b[38;5;252m \u001b[0m\u001b[38;5;252m \u001b[0m\u001b[38;5;252m \u001b[0m\u001b[38;5;252m \u001b[0m\u001b[38;5;252m \u001b[0m\u001b[38;5;252m \u001b[0m\u001b[38;5;252m \u001b[0m\u001b[38;5;252m \u001b[0m\u001b[38;5;252m \u001b[0m\u001b[38;5;252m \u001b[0m\u001b[38;5;252m \u001b[0m\u001b[38;5;252m \u001b[0m\u001b[38;5;252m \u001b[0m\u001b[38;5;252m \u001b[0m\u001b[38;5;252m \u001b[0m\u001b[38;5;252m \u001b[0m\u001b[38;5;252m \u001b[0m\u001b[38;5;252m \u001b[0m\u001b[38;5;252m \u001b[0m\u001b[38;5;252m \u001b[0m\u001b[38;5;252m \u001b[0m\u001b[38;5;252m \u001b[0m\u001b[38;5;252m \u001b[0m\u001b[38;5;252m \u001b[0m\u001b[38;5;252m \u001b[0m\u001b[38;5;252m \u001b[0m\u001b[38;5;252m \u001b[0m\u001b[38;5;252m \u001b[0m\u001b[38;5;252m \u001b[0m\u001b[38;5;252m \u001b[0m\u001b[38;5;252m \u001b[0m\u001b[38;5;252m \u001b[0m\u001b[38;5;252m \u001b[0m\u001b[38;5;252m \u001b[0m\u001b[38;5;252m \u001b[0m\u001b[38;5;252m \u001b[0m\u001b[38;5;252m \u001b[0m\u001b[38;5;252m \u001b[0m\u001b[38;5;252m \u001b[0m\u001b[38;" ]
[ 22.45029, "o", "5;252m \u001b[0m\u001b[38;5;252m \u001b[0m\u001b[38;5;252m \u001b[0m\u001b[38;5;252m \u001b[0m\u001b[38;5;252m \u001b[0m\u001b[38;5;252m \u001b[0m\u001b[38;5;252m \u001b[0m\u001b[38;5;252m \u001b[0m\u001b[38;5;252m \u001b[0m\u001b[38;5;252m \u001b[0m\u001b[38;5;252m \u001b[0m\u001b[38;5;252m \u001b[0m\u001b[38;5;252m \u001b[0m\u001b[38;5;252m \u001b[0m\u001b[38;5;252m \u001b[0m\u001b[38;5;252m \u001b[0m\u001b[38;5;252m \u001b[0m\u001b[38;5;252m \u001b[0m\u001b[38;5;252m \u001b[0m\u001b[38;5;252m \u001b[0m\u001b[38;5;252m \u001b[0m\u001b[38;5;252m \u001b[0m\u001b[38;5;252m \u001b[0m\u001b[38;5;252m \u001b[0m\u001b[38;5;252m \u001b[0m\u001b[38;5;252m \u001b[0m\u001b[38;5;252m \u001b[0m\u001b[38;5;252m \u001b[0m\u001b[38;5;252m \u001b[0m\u001b[38;5;252m \u001b[0m\u001b[38;5;252m \u001b[0m\u001b[38;5;252m \u001b[0m\u001b[38;5;252m \u001b[0m\u001b[38;5;252m \u001b[0m\u001b[38;5;252m \u001b[0m\u001b[38;5;252m \u001b[0m\u001b[38;5;252m \u001b[0m\u001b[38;5;252m \u001b[0m\u001b[38;5;252m \u001b[0m\u001b[38;5;252m \u001b[0m\u001b[38;5;252m \u001b[0m\u001b[38;5;252m \u001b[0m\u001b[38;5;252m \u001b[0m\r\r\n\u001b[38;5;35;1m\u001b[0m\u001b[38;5;35;1m\u001b[0m  \u001b[38;5;35;1mMIT\u001b[0m\u001b[38;5;252m \u001b[0m\u001b[38;5;30;4mhttps://github.com/charmbracelet/glow/raw/master/LICENSE\u001b[0m\u001b[38;5;252m \u001b[0m\u001b[38;5;252m \u001b[0m\u001b[38;5;252m \u001b[0m\u001b[38;5;252m \u001b[0m\u001b[38;5;252m \u001b[0m\u001b[38;5;252m \u001b[0m\u001b[38;5;252m \u001b[0m\u001b[38;5;252m \u001b[0m\u001b[38;5;252m \u001b[0m\u001b[38;5;252m \u001b[0m\u001b[38;5;252m \u001b[0m\u001b[38;5;252m \u001b[0m\u001b[38;" ]
[ 22.45074, "o", "5;252m \u001b[0m\u001b[38;5;252m \u001b[0m\u001b[38;5;252m \u001b[0m\u001b[38;5;252m \u001b[0m\u001b[38;5;252m \u001b[0m\u001b[38;5;252m \u001b[0m\u001b[38;5;252m \u001b[0m\u001b[38;5;252m \u001b[0m\u001b[38;5;252m \u001b[0m\u001b[38;5;252m \u001b[0m\u001b[38;5;252m \u001b[0m\u001b[38;5;252m \u001b[0m\u001b[38;5;252m \u001b[0m\u001b[38;5;252m \u001b[0m\u001b[38;5;252m \u001b[0m\u001b[38;5;252m \u001b[0m\u001b[38;5;252m \u001b[0m\u001b[38;5;252m \u001b[0m\u001b[38;5;252m \u001b[0m\u001b[38;5;252m \u001b[0m\u001b[38;5;252m \u001b[0m\u001b[38;5;252m \u001b[0m\u001b[38;5;252m \u001b[0m\u001b[38;5;252m \u001b[0m\r\r\n\u001b[38;5;240m\u001b[0m  \u001b[38;5;240m\u001b[38;5;252m \u001b[0m\u001b[38;5;252m \u001b[0m\u001b[38;5;252m \u001b[0m\u001b[38;5;252m \u001b[0m\u001b[38;5;252m \u001b[0m\u001b[38;5;252m \u001b[0m\u001b[38;5;252m \u001b[0m\u001b[38;5;252m \u001b[0m\u001b[38;5;252m \u001b[0m\u001b[38;5;252m \u001b[0m\u001b[38;5;252m \u001b[0m\u001b[38;5;252m \u001b[0m\u001b[38;5;252m \u001b[0m\u001b[38;5;252m \u001b[0m\u001b[38;5;252m \u001b[0m\u001b[38;5;252m \u001b[0m\u001b[38;5;252m \u001b[0m\u001b[38;5;252m \u001b[0m\u001b[38;5;252m \u001b[0m\u001b[38;5;252m \u001b[0m\u001b[38;5;252m \u001b[0m\u001b[38;5;252m \u001b[0m\u001b[38;5;252m \u001b[0m\u001b[38;5;252m \u001b[0m\u001b[38;5;252m \u001b[0m\u001b[38;5;252m \u001b[0m\u001b[38;5;252m \u001b[0m\u001b[38;5;252m \u001b[0m\u001b[38;5;252m \u001b[0m\u001b[38;5;252m \u001b[0m\u001b[38;5;252m \u001b[0m\u001b[38;5;252m \u001b[0m\u001b[38;5;252m \u001b[0m\u001b[38;5;252m \u001b[0m\u001b[38;5;252m \u001b[0m\u001b[38;5;252m \u001b[0m\u001b[38;5;252m \u001b[0m\u001b[38;5;252m \u001b[0m\u001b[38;5" ]
[ 22.45089, "o", ";252m \u001b[0m\u001b[38;5;252m \u001b[0m\u001b[38;5;252m \u001b[0m\u001b[38;5;252m \u001b[0m\u001b[38;5;252m \u001b[0m\u001b[38;5;252m \u001b[0m\u001b[38;5;252m \u001b[0m\u001b[38;5;252m \u001b[0m\u001b[38;5;252m \u001b[0m\u001b[38;5;252m \u001b[0m\u001b[38;5;252m \u001b[0m\u001b[38;5;252m \u001b[0m\u001b[38;5;252m \u001b[0m\u001b[38;5;252m \u001b[0m\u001b[38;5;252m \u001b[0m\u001b[38;5;252m \u001b[0m\u001b[38;5;252m \u001b[0m\u001b[38;5;252m \u001b[0m\u001b[38;5;252m \u001b[0m\u001b[38;5;252m \u001b[0m\u001b[38;5;252m \u001b[0m\u001b[38;5;252m \u001b[0m\u001b[38;5;252m \u001b[0m\u001b[38;5;252m \u001b[0m\u001b[38;5;252m \u001b[0m\u001b[38;5;252m \u001b[0m\u001b[38;5;252m \u001b[0m\u001b[38;5;252m \u001b[0m\u001b[38;5;252m \u001b[0m\u001b[38;5;252m \u001b[0m\u001b[38;5;252m \u001b[0m\u001b[38;5;252m \u001b[0m\u001b[38;5;252m \u001b[0m\u001b[38;5;252m \u001b[0m\u001b[38;5;252m \u001b[0m\u001b[38;5;252m \u001b[0m\u001b[38;5;252m \u001b[0m\u001b[38;5;252m \u001b[0m\u001b[38;5;252m \u001b[0m\u001b[38;5;252m \u001b[0m\u001b[38;5;252m \u001b[0m\u001b[38;5;252m \u001b[0m\u001b[38;5;252m \u001b[0m\u001b[38;5;252m \u001b[0m\u001b[38;5;252m \u001b[0m\u001b[38;5;252m \u001b[0m\u001b[38;5;252m \u001b[0m\u001b[38;5;252m \u001b[0m\u001b[38;5;252m \u001b[0m\u001b[38;5;252m \u001b[0m\u001b[38;5;252m \u001b[0m\u001b[38;5;252m \u001b[0m\u001b[38;5;252m \u001b[0m\u001b[38;5;252m \u001b[0m\u001b[38;5;252m \u001b[0m\u001b[38;5;252m \u001b[0m\u001b[38;5;252m \u001b[0m\u001b[38;5;252m \u001b[0m\u001b[0m\r\r\n\u001b[0m  \u001b[38;5;240m--------\u001b[38;5;252m \u001b[0m\u001b[38;5;252m \u001b[0m\u001b[38;5;252m \u001b[0m\u001b[38;5;252m \u001b[0m\u001b[38;5" ]
[ 22.45092, "o", ";252m \u001b[0m\u001b[38;5;252m \u001b[0m\u001b[38;5;252m \u001b[0m\u001b[38;5;252m \u001b[0m\u001b[38;5;252m \u001b[0m\u001b[38;5;252m \u001b[0m\u001b[38;5;252m \u001b[0m\u001b[38;5;252m \u001b[0m\u001b[38;5;252m \u001b[0m\u001b[38;5;252m \u001b[0m\u001b[38;5;252m \u001b[0m\u001b[38;5;252m \u001b[0m\u001b[38;5;252m \u001b[0m\u001b[38;5;252m \u001b[0m\u001b[38;5;252m \u001b[0m\u001b[38;5;252m \u001b[0m\u001b[38;5;252m \u001b[0m\u001b[38;5;252m \u001b[0m\u001b[38;5;252m \u001b[0m\u001b[38;5;252m \u001b[0m\u001b[38;5;252m \u001b[0m\u001b[38;5;252m \u001b[0m\u001b[38;5;252m \u001b[0m\u001b[38;5;252m \u001b[0m\u001b[38;5;252m \u001b[0m\u001b[38;5;252m \u001b[0m\u001b[38;5;252m \u001b[0m\u001b[38;5;252m \u001b[0m\u001b[38;5;252m \u001b[0m\u001b[38;5;252m \u001b[0m\u001b[38;5;252m \u001b[0m\u001b[38;5;252m \u001b[0m\u001b[38;5;252m \u001b[0m\u001b[38;5;252m \u001b[0m\u001b[38;5;252m \u001b[0m\u001b[38;5;252m \u001b[0m\u001b[38;5;252m \u001b[0m\u001b[38;5;252m \u001b[0m\u001b[38;5;252m \u001b[0m\u001b[38;5;252m \u001b[0m\u001b[38;5;252m \u001b[0m\u001b[38;5;252m \u001b[0m\u001b[38;5;252m \u001b[0m\u001b[38;5;252m \u001b[0m\u001b[38;5;252m \u001b[0m\u001b[38;5;252m \u001b[0m\u001b[38;5;252m \u001b[0m\u001b[38;5;252m \u001b[0m\u001b[38;5;252m \u001b[0m\u001b[38;5;252m \u001b[0m\u001b[38;5;252m \u001b[0m\u001b[38;5;252m \u001b[0m\u001b[38;5;252m \u001b[0m\u001b[38;5;252m \u001b[0m\u001b[38;5;252m \u001b[0m\u001b[38;5;252m \u001b[0m\u001b[38;5;252m \u001b[0m\u001b[38;5;252m \u001b[0m\u001b[38;5;252m \u001b[0m\u001b[38;5;252m \u001b[0m\u001b[38;5;252m \u001b[0m\u001b[38;5;252m \u001b[0m\u001b[38;5;252m \u001b[0m\u001b[38;5;252m \u001b[0m\u001b[38;5" ]
[ 22.45104, "o", ";252m \u001b[0m\u001b[38;5;252m \u001b[0m\u001b[38;5;252m \u001b[0m\u001b[38;5;252m \u001b[0m\u001b[38;5;252m \u001b[0m\u001b[38;5;252m \u001b[0m\u001b[38;5;252m \u001b[0m\u001b[38;5;252m \u001b[0m\u001b[38;5;252m \u001b[0m\u001b[38;5;252m \u001b[0m\u001b[38;5;252m \u001b[0m\u001b[38;5;252m \u001b[0m\u001b[38;5;252m \u001b[0m\u001b[38;5;252m \u001b[0m\u001b[38;5;252m \u001b[0m\u001b[38;5;252m \u001b[0m\u001b[38;5;252m \u001b[0m\u001b[38;5;252m \u001b[0m\u001b[38;5;252m \u001b[0m\u001b[38;5;252m \u001b[0m\u001b[0m\r\r\n\u001b[0m  \u001b[38;5;252m \u001b[0m\u001b[38;5;252m \u001b[0m\u001b[38;5;252m \u001b[0m\u001b[38;5;252m \u001b[0m\u001b[38;5;252m \u001b[0m\u001b[38;5;252m \u001b[0m\u001b[38;5;252m \u001b[0m\u001b[38;5;252m \u001b[0m\u001b[38;5;252m \u001b[0m\u001b[38;5;252m \u001b[0m\u001b[38;5;252m \u001b[0m\u001b[38;5;252m \u001b[0m\u001b[38;5;252m \u001b[0m\u001b[38;5;252m \u001b[0m\u001b[38;5;252m \u001b[0m\u001b[38;5;252m \u001b[0m\u001b[38;5;252m \u001b[0m\u001b[38;5;252m \u001b[0m\u001b[38;5;252m \u001b[0m\u001b[38;5;252m \u001b[0m\u001b[38;5;252m \u001b[0m\u001b[38;5;252m \u001b[0m\u001b[38;5;252m \u001b[0m\u001b[38;5;252m \u001b[0m\u001b[38;5;252m \u001b[0m\u001b[38;5;252m \u001b[0m\u001b[38;5;252m \u001b[0m\u001b[38;5;252m \u001b[0m\u001b[38;5;252m \u001b[0m\u001b[38;5;252m \u001b[0m\u001b[38;5;252m \u001b[0m\u001b[38;5;252m \u001b[0m\u001b[38;5;252m \u001b[0m\u001b[38;5;252m \u001b[0m\u001b[38;5;252m \u001b[0m\u001b[38;5;252m \u001b[0m\u001b[38;5;252m \u001b[0m\u001b[38;5;252m \u001b[0m\u001b[38;5;252m \u001b[0m\u001b[38;5;252m \u001b[0m\u001b[38;5;252m \u001b[0m\u001b[38;5;252m \u001b[0m\u001b[38;5;252m \u001b[0m\u001b[38;5;25" ]
[ 22.45124, "o", "2m \u001b[0m\u001b[38;5;252m \u001b[0m\u001b[38;5;252m \u001b[0m\u001b[38;5;252m \u001b[0m\u001b[38;5;252m \u001b[0m\u001b[38;5;252m \u001b[0m\u001b[38;5;252m \u001b[0m\u001b[38;5;252m \u001b[0m\u001b[38;5;252m \u001b[0m\u001b[38;5;252m \u001b[0m\u001b[38;5;252m \u001b[0m\u001b[38;5;252m \u001b[0m\u001b[38;5;252m \u001b[0m\u001b[38;5;252m \u001b[0m\u001b[38;5;252m \u001b[0m\u001b[38;5;252m \u001b[0m\u001b[38;5;252m \u001b[0m\u001b[38;5;252m \u001b[0m\u001b[38;5;252m \u001b[0m\u001b[38;5;252m \u001b[0m\u001b[38;5;252m \u001b[0m\u001b[38;5;252m \u001b[0m\u001b[38;5;252m \u001b[0m\u001b[38;5;252m \u001b[0m\u001b[38;5;252m \u001b[0m\u001b[38;5;252m \u001b[0m\u001b[38;5;252m \u001b[0m\u001b[38;5;252m \u001b[0m\u001b[38;5;252m \u001b[0m\u001b[38;5;252m \u001b[0m\u001b[38;5;252m \u001b[0m\u001b[38;5;252m \u001b[0m\u001b[38;5;252m \u001b[0m\u001b[38;5;252m \u001b[0m\u001b[38;5;252m \u001b[0m\u001b[38;5;252m \u001b[0m\u001b[38;5;252m \u001b[0m\u001b[38;5;252m \u001b[0m\u001b[38;5;252m \u001b[0m\u001b[38;5;252m \u001b[0m\u001b[38;5;252m \u001b[0m\u001b[38;5;252m \u001b[0m\u001b[38;5;252m \u001b[0m\u001b[38;5;252m \u001b[0m\u001b[38;5;252m \u001b[0m\u001b[38;5;252m \u001b[0m\u001b[38;5;252m \u001b[0m\u001b[38;5;252m \u001b[0m\u001b[38;5;252m \u001b[0m\u001b[38;5;252m \u001b[0m\u001b[38;5;252m \u001b[0m\u001b[38;5;252m \u001b[0m\u001b[38;5;252m \u001b[0m\r\r\n\u001b[38;5;252m\u001b[0m\u001b[38;5;252m\u001b[0m  \u001b[38;5;252mPart of \u001b[0m\u001b[38;5;35;1mCharm\u001b[0m\u001b[38;5;252m \u001b[0m\u001b[38;5;30;4mhttps://charm.sh\u001b[0m\u001b[38;5;252m. \u001b[0m\u001b[38;5;252m \u001b[0m\u001b[38;5;252mCharm热爱开" ]
[ 22.45129, "o", "源 • Charm loves open\u001b[0m\u001b[38;5;252m source\u001b[0m\u001b[38;5;252m \u001b[0m\u001b[38;5;252m \u001b[0m\u001b[38;5;252m \u001b[0m\u001b[38;5;252m \u001b[0m\u001b[38;5;252m \u001b[0m\u001b[38;5;252m \u001b[0m\u001b[38;5;252m \u001b[0m\u001b[38;5;252m \u001b[0m\u001b[38;5;252m \u001b[0m\u001b[38;5;252m \u001b[0m\u001b[38;5;252m \u001b[0m\u001b[38;5;252m \u001b[0m\u001b[38;5;252m \u001b[0m\u001b[38;5;252m \u001b[0m\u001b[38;5;252m \u001b[0m\u001b[38;5;252m \u001b[0m\u001b[38;5;252m \u001b[0m\u001b[38;5;252m \u001b[0m\u001b[38;5;252m \u001b[0m\u001b[38;5;252m \u001b[0m\u001b[38;5;252m \u001b[0m\u001b[38;5;252m \u001b[0m\u001b[38;5;252m \u001b[0m\u001b[38;5;252m \u001b[0m\r\r\n\r\r\n\u001b[0;26r\u001b[26;0H" ]
[ 22.45248, "o", "\u001b[2K\u001b[1A\u001b[1A\u001b[1A\u001b[1A\u001b[1A\u001b[1A\u001b[1A\u001b[1A\u001b[1A\u001b[1A\u001b[1A\u001b[1A\u001b[1A\u001b[1A\u001b[1A\u001b[1A\u001b[1A\u001b[1A\u001b[1A\u001b[1A\u001b[1A\u001b[1A\u001b[1A\u001b[1A\u001b[1A\u001b[1B\u001b[1B\u001b[1B\u001b[1B\u001b[1B\u001b[1B\u001b[1B\u001b[1B\u001b[1B\u001b[1B\u001b[1B\u001b[1B\u001b[1B\u001b[1B\u001b[1B\u001b[1B\u001b[1B\u001b[1B\u001b[1B\u001b[1B\u001b[1B\u001b[1B\u001b[1B\u001b[1B\u001b[1B\u001b[1;;m Glow \u001b[0m\u001b[;m README.md \u001b[0m\u001b[;m                                                                     \u001b[0m\u001b[;m 100% \u001b[0m\u001b[;m ? Help \u001b[0m\u001b[26;0H" ]
[ 25.44855, "o", "\u001b[2K\u001b[?25h\u001b[?1002l\u001b[?1003l\u001b[?1049l\u001b[?25h" ]
[ 25.46047, "o", "\u001b[1m\u001b[7m#\u001b[27m\u001b[1m\u001b[0m                                                                                                   \r \r\r\u001b[0m\u001b[27m\u001b[24m\u001b[J\r\n\u001b[19491001\u001b[1;35m> \u001b[20210325\u001b[0m\u001b[K\u001b[?2004h" ]
[ 26.50226, "o", "e" ]
[ 26.55455, "o", "\bex" ]
[ 26.60719, "o", "i" ]
[ 26.65890, "o", "t" ]
[ 27.71291, "o", "\u001b[?2004l\r\r" ]
